[{"choose":["恋","潋","链","炼"],"answer":"炼","pinyin":"jīng liàn","id":1,"discrimination":"liàn：精（炼）\n留（恋）\n（潋）滟\n铁（链）","title":"精()","source":"2014贺州","explanation":"1.除去杂质，提取精华。2.同精练。指（文章或讲话）扼要，没有多余的词句。","label":1,"words":"精炼"},{"choose":["宛","腕","婉","蜿"],"answer":"腕","pinyin":"shǒu wàn","id":2,"discrimination":"wàn：手（腕）\nwǎn：（宛）如\n委（婉）\nwān：（蜿）蜒","title":"手()","source":"2016贺州","explanation":"1.待人处世的不正当方法。2.本领；方法和技巧。3.为达到某一目的而采取的方法或手段。","label":2,"words":"手腕"},{"choose":["藉","嵇","籍","暨"],"answer":"籍","pinyin":"diǎn jí","id":3,"discrimination":"jí：典（籍）\njiè：慰（藉）\njī：（嵇）阮\njì：（暨）今","title":"典()","source":"2014玉林、2014防城港","explanation":"1.古代重要文献的总称。在不同领域，有不同的代表性典籍。2.泛指古代图书。","label":3,"words":"典籍"},{"choose":["悬","玄","旋","璇"],"answer":"悬","pinyin":"xuán niàn","id":4,"discrimination":"xuán：（悬）念\n（玄）妙\n凯（旋）\n（璇）玑","title":"()念","source":"2014河池","explanation":"1.挂念。2.欣赏文艺作品或影视戏剧时，对情节发展和人物命运的关切心情。","label":1,"words":"悬念"},{"choose":["诠","栓","全","醛"],"answer":"诠","pinyin":"quán shì","id":5,"discrimination":"quán：（诠）释\n（全）部\n甲（醛）\nshuān：（拴）住","title":"()释","source":"2016钦州","explanation":"1.加进书中的一段评论或解释性的文字。2.解说；解释；阐明。","label":2,"words":"诠释"},{"choose":["谨","瑾","槿","矜"],"answer":"谨","pinyin":"jǐn yán","id":6,"discrimination":"jǐn：（谨）言\n（瑾）瑜\n木（槿）花","title":"()言","source":"2015柳州","explanation":"指审慎发言。","label":4,"words":"谨言"},{"choose":["谚","研","炎","妍"],"answer":"妍","pinyin":"zhēng yán dòu yàn","id":7,"discrimination":"yán：争（妍）斗艳\n钻（研）\n（炎）热\nyàn：（谚）语","title":"争()斗艳","source":"2016北海","explanation":"指竞相比美。","label":3,"words":"争妍斗艳"},{"choose":["卷","拳","蜷","绻"],"answer":"蜷","pinyin":"quán qū","id":8,"discrimination":"quán：（蜷）曲\njuǎn：（卷）住\nquǎn：缱（绻）","title":"()曲","source":"2017贺州","explanation":"弯曲（多用于人或动物的肢体）。","label":2,"words":"蜷曲"},{"choose":["谈","炎","弹","淡"],"answer":"淡","pinyin":"dàn yǎ","id":9,"discrimination":"dàn：（淡）雅\ntán：（谈）话\nyán：（炎）热","title":"()雅","source":"2016崇左","explanation":"1.素净雅致。2.（花草等的香气）清淡。","label":2,"words":"淡雅"},{"choose":["蔬","毓","疏","梳"],"answer":"疏","pinyin":"shū mì","id":10,"discrimination":"shū：（疏）密\n（蔬）菜\n（梳）子\nyù：钟灵（毓）秀","title":"()密","source":"2015南宁","explanation":"1.稀疏与稠密。2.疏远与亲密。3.松散与坚密。","label":2,"words":"疏密"},{"choose":["瑾","槿","勤","谨"],"answer":"谨","pinyin":"yán jǐn","id":11,"discrimination":"jǐn：严（谨）\n（瑾）瑜\n木（槿）\nqín：（勤）快","title":"严()","source":"2015玉林、2015防城港","explanation":"1.严肃谨慎。2.严密。","label":2,"words":"严谨"},{"choose":["高","镐","搞","犒"],"answer":"犒","pinyin":"kào láo","id":12,"discrimination":"kào：（犒）劳\ngāo：（高）低\nhào：（镐）京\ngǎo：（搞）定","title":"()劳","source":"2016河池","explanation":"1.用酒食等慰劳。2.用来慰劳的酒食等。","label":2,"words":"犒劳"},{"choose":["磬","馨","磐","欣"],"answer":"馨","pinyin":"fāng xīn","id":13,"discrimination":"xīn：芳（馨）\nqìng：（磬）笔难书\npán：（磐）石","title":"芳()","source":"2014南宁","explanation":"芳香。","label":2,"words":"芳馨"},{"choose":["啸","潇","萧","肃"],"answer":"萧","pinyin":"xiāo tiáo","id":14,"discrimination":"xiāo：（萧）条\n（潇）洒\nxiào：呼（啸）\nsù：严（肃）","title":"()条","source":"2017河池","explanation":"1.指寂寥冷清的样子。2.经济不景气。","label":2,"words":"萧条"},{"choose":["衲","纳","讷","呐"],"answer":"讷","pinyin":"mù nè","id":15,"discrimination":"nè：木（讷）\nnà：老（衲）\n收（纳）\n（呐）喊","title":"木()","source":"2014贵港","explanation":"朴实迟钝，不善于说话。","label":2,"words":"木讷"},{"choose":["珞","络","洛","烙"],"answer":"络","pinyin":"mài luò","id":16,"discrimination":"luò：脉（络）\n璎（珞）\n（洛）阳\nlào：（烙）印","title":"脉()","source":"2014贺州","explanation":"1.中医对动脉和静脉的统称。2.比喻条理或头绪。3.维管植物的维管系统。","label":2,"words":"脉络"},{"choose":["班","般","斑","癍"],"answer":"斑","pinyin":"bān mǎ xiàn","id":17,"discrimination":"bān：（斑）马线\n（班）级\n（癍）点","title":"()马线","source":"2015钦州","explanation":"一般是由多条相互平行的白实线组成，好似斑马身上的线条，所以称作“斑马线”。斑马线作用是能引导行人安全地过马路。出现在20世纪50年代初期。","label":4,"words":"斑马线"},{"choose":["裨","碑","卑","备"],"answer":"裨","pinyin":"bì  yì","id":18,"discrimination":"bì：（裨）益\nbēi：墓（碑）\n（卑）鄙","title":"()益","source":"2014北海","explanation":"裨：增添，补助。益处；使受益。","label":2,"words":"裨益"},{"choose":["搏","博","薄","泊"],"answer":"博","pinyin":"dì dà wù bó","id":19,"discrimination":"bó：地大物（博）\n（搏）斗\n（薄）利多销","title":"地大物()","source":"2017河池","explanation":"博：丰富。指国家疆土辽阔，资源丰富。","label":4,"words":"地大物博"},{"choose":["溉","概","慨","既"],"answer":"慨","pinyin":"kāng kǎi dà fāng","id":20,"discrimination":"kǎi：慷（慨）大方\ngài：灌（溉）\n大（概）\njì：（既）然","title":"慷()大方","source":"2017梧州","explanation":"不吝啬、不小气，不看重钱财。","label":2,"words":"慷慨大方"},{"choose":["恻","册","侧","策"],"answer":"策","pinyin":"shù shǒu wú cè","id":1,"discrimination":"cè：束手无（策）\n（恻）隐\n（册）子\n（侧）面","title":"束手无()","source":"2015梧州","explanation":"策：办法。遇到问题，就像手被捆住一样，一点办法也没有。","label":1,"words":"束手无策"},{"choose":["姹","诧","宅","咤"],"answer":"姹","pinyin":"chà zǐ yān hóng","id":2,"discrimination":"chà：（姹）紫嫣红\n（诧）异\nzhái：（宅）子\nzhà：叱（咤）风云","title":"()紫嫣红","source":"2015河池、2014北海","explanation":"姹、嫣：娇艳。形容各种花朵娇艳美丽。","label":2,"words":"姹紫嫣红"},{"choose":["到","悼","盗","道"],"answer":"道","pinyin":"dào tīng tú shuō","id":3,"discrimination":"dào：（道）听途说\n（到）达\n（悼）念\n（盗）窃","title":"()听途说","source":"2014钦州","explanation":"道、途：路。路上听来的、路上传播的话。泛指没有根据的传闻。","label":1,"words":"道听途说"},{"choose":["宏","弘","红","虹"],"answer":"虹","pinyin":"ní hóng dēng","id":4,"discrimination":"hóng：霓（虹）灯\n（宏）伟\n（弘）扬\n（鲜）红","title":"霓()灯","source":"2014钦州","explanation":"灯的一种，在真空中玻璃管内充入氖，两端安装电极，通电后发出红色或蓝色的光。多用做广告灯或信号灯。","label":1,"words":"霓虹灯"},{"choose":["风","峰","封","丰"],"answer":"峰","pinyin":"dēng fēng zào jí","id":5,"discrimination":"fēng：登（峰）造极\n（风）车\n（封）印\n（丰）富","title":"登()造极","source":"2014钦州","explanation":"登：上；峰：山顶；造：到达；极：最高点。比喻学问、技能等达到最高的境界或成就。","label":1,"words":"登峰造极"},{"choose":["疑","宁","凝","咛"],"answer":"凝","pinyin":"níng móu","id":6,"discrimination":"níng：（凝）眸\n（宁）静\n叮（咛）\nyí：（疑）惑","title":"()眸","source":"2015玉林、2015防城港","explanation":"目不转睛。形容观察或欣赏事物时注意力高度集中。","label":3,"words":"凝眸"},{"choose":["流","留","梳","硫"],"answer":"流","pinyin":"duì dá rú liú","id":7,"discrimination":"liú：对答如（流）\n（硫）磺\nshū：（梳）子","title":"对答如()","source":"2014来宾、2014南宁","explanation":"对答：回答。回答问话象流水一样快。形容口才好，反应快。","label":2,"words":"对答如流"},{"choose":["衔","街","衙","衍"],"answer":"衍","pinyin":"fán yǎn","id":8,"discrimination":"yǎn：繁（衍）\nxián：（衔）接\njiē：（街）坊\nyá：（衙）门","title":"繁()","source":"2016百色","explanation":"逐渐增多或增广。","label":2,"words":"繁衍"},{"choose":["蓦","幕","慕","募"],"answer":"慕","pinyin":"kě mù","id":9,"discrimination":"mù：渴（慕）\n（幕）布\n（募）捐\nmò：（蓦）然","title":"渴()","source":"2017梧州","explanation":"非常向往。","label":2,"words":"渴慕"},{"choose":["扑扑","卜卜","仆仆","朴朴"],"answer":"仆仆","pinyin":"fēng chén pú pú","id":10,"discrimination":"pú：风尘（仆）（仆）\npū：粉（扑）\nbo：萝（卜）\npǔ：（朴）素","title":"风尘()()","source":"2016河池","explanation":"风尘：指行旅，含有辛苦之意；仆仆：行路劳累的样子。形容旅途奔波，忙碌劳累。","label":2,"words":"风尘仆仆"},{"choose":["翩翩","篇篇","片片","偏偏"],"answer":"翩翩","pinyin":"fēng dù piān piān","id":11,"discrimination":"piān：风度（翩）（翩）\n（篇）目\n（偏）爱","title":"风度()()","source":"2017桂林、2014河池","explanation":"风度：风采气度，指美好的举止姿态；翩翩：文雅的样子。举止文雅优美。","label":4,"words":"风度翩翩"},{"choose":["旗","棋","其","骑"],"answer":"旗","pinyin":"qí kāi dé shèng","id":12,"discrimination":"qí：（旗）开得胜\n围（棋）\n（其）中","title":"()开得胜","source":"2014北海","explanation":"刚一打开旗帜进入战斗，就取得了胜利。比喻事情刚一开始，就取得好成绩。","label":4,"words":"旗开得胜"},{"choose":["躬","攻","供","功"],"answer":"供","pinyin":"gōng yǎng","id":13,"discrimination":"gōng：（供）养\n鞠（躬）\n进（攻）\n（功）课","title":"()养","source":"2014贵港","explanation":"供给长辈或年长的人生活所需；赡养。","label":1,"words":"供养"},{"choose":["辟","僻","避","劈"],"answer":"辟","pinyin":"kāi tiān pì dì","id":14,"discrimination":"pì：开天（辟）地\n偏（僻）\nbì：躲（避）\npī：（劈）开","title":"开天()地","source":"2014贺州","explanation":"古代神话传说：盘古氏开辟天地，开始有人类历史。后常比喻空前的，自古以来没有过的。","label":2,"words":"开天辟地"},{"choose":["煌","皇","惶","璜"],"answer":"煌","pinyin":"huī huáng","id":15,"discrimination":"huáng：辉（煌）\n（皇）家\n（惶）恐","title":"辉()","source":"2016崇左","explanation":"光辉灿烂的意思。","label":4,"words":"辉煌"},{"choose":["藉","嵇","暨","籍"],"answer":"籍","pinyin":"guó jí","id":16,"discrimination":"jí：国（籍）\njiè：慰（藉）\njī：（嵇）阮\njì：（暨）今","title":"国()","source":"2015柳州","explanation":"指一个人属于某一个国家的国民或公民的法律资格，表明一个人同一个特定国家间的固定的法律联系，是国家行使属人管辖权和外交保护权的法律顾问依据。","label":3,"words":"国籍"},{"choose":["宏","弘","虹","鸿"],"answer":"鸿","pinyin":"hóng rú","id":17,"discrimination":"hóng：（鸿）儒\n（宏）伟\n恢（弘）\n彩（虹）","title":"()儒","source":"2017广西北部湾经济区四市同城","explanation":"指博学的人。","label":1,"words":"鸿儒"},{"choose":["索","萤","莹","萦"],"answer":"萦","pinyin":"yíng huí","id":18,"discrimination":"yíng：（萦）回\n（萤）火虫\n晶（莹）\nsuǒ：（索）要","title":"()回","source":"2017桂林","explanation":"回旋环绕。","label":2,"words":"萦回"},{"choose":["骚","搔","蚤","瘙"],"answer":"骚","pinyin":"sāo luàn","id":19,"discrimination":"sāo：（骚）乱\n（搔）头\nzǎo：跳（蚤）\nsào：（瘙）痒","title":"()乱","source":"2014桂林","explanation":"混乱不安定；动乱。","label":2,"words":"骚乱"},{"choose":["腱","健","键","建"],"answer":"腱","pinyin":"jī jiàn","id":20,"discrimination":"jiàn：肌（腱）\n（健）康\n（键）盘\n（建）立","title":"肌()","source":"2017梧州","explanation":"肌腹两端的索状或膜状致密结缔组织，便于肌肉附着和固定。","label":4,"words":"肌腱"},{"choose":["极","圾","及","汲"],"answer":"及","pinyin":"biān cháng mò jí","id":1,"discrimination":"jí：鞭长莫（及）\n（极）光\n（汲）水\njī：垃（圾）","title":"鞭长莫()","source":"2015桂林","explanation":"及：到。原意是鞭子虽长，也不能打马肚子。比喻相隔太远，力量达不到。","label":2,"words":"鞭长莫及"},{"choose":["璧","碧","臂","壁"],"answer":"壁","pinyin":"jué bì","id":2,"discrimination":"bì：绝（壁）\n完（璧）归赵\n手（臂）","title":"绝()","source":"2015贺州","explanation":"极陡峭不能攀援的山崖。","label":4,"words":"绝壁"},{"choose":["劫","怯","却","励"],"answer":"劫","pinyin":"jié hòu yú shēng","id":3,"discrimination":"jié：（劫）后余生\nqiè：胆（怯）\nquè：望而（却）步","title":"()后余生","source":"2014桂林","explanation":"劫：灾难；余生：侥幸保全的生命。经历灾难以后幸存下来的生命。","label":2,"words":"劫后余生"},{"choose":["经","精","惊","睛"],"answer":"精","pinyin":"jīng pí lì jié","id":4,"discrimination":"jīng：（精）疲力竭\n（经）过\n（惊）讶\n眼（睛）","title":"()疲力竭","source":"2015南宁","explanation":"竭：尽。精神、力气消耗已尽。形容非常疲劳。","label":1,"words":"精疲力竭"},{"choose":["律","津","肄","肆"],"answer":"津","pinyin":"jīn jīn yǒu wèi","id":5,"discrimination":"jīn：（津）（津）有味\nlǜ：（律）师\nyì：（肄）业\nsì：（肆）无忌惮","title":"()()有味","source":"2014河池","explanation":"津津：兴趣浓厚的样子。指吃得很有味道或谈得很有兴趣。","label":2,"words":"津津有味"},{"choose":["睫","劫","捷","婕"],"answer":"捷","pinyin":"jié jìng","id":6,"discrimination":"jié：（捷）径\n（睫）毛\n班（婕）","title":"()径","source":"2014桂林","explanation":"近路，比喻能较快地达到目的的巧妙手段或办法。","label":4,"words":"捷径"},{"choose":["检","俭","睑","捡"],"answer":"俭","pinyin":"kè qín kè jiǎn","id":7,"discrimination":"jiǎn：克勤克（俭）\n（检）查\n眼（睑）\n拾（捡）","title":"克勤克()","source":"2017桂林、2014北海","explanation":"克：能够。既能勤劳，又能节俭。","label":4,"words":"克勤克俭"},{"choose":["舞","妩","午","武"],"answer":"武","pinyin":"kǒng wǔ yǒu lì","id":8,"discrimination":"wǔ：孔（武）有力\n（舞）蹈\n（妩）媚\n（午）餐","title":"孔()有力","source":"2015桂林","explanation":"孔：甚，很。形容人很有力气。","label":1,"words":"孔武有力"},{"choose":["亏","归","跬","岿"],"answer":"岿","pinyin":"kuī rán bù dòng","id":9,"discrimination":"kuī：（岿）然不动\n（亏）本\nguī：（归）还\nkuǐ：（跬）步","title":"()然不动","source":"2015北海","explanation":"岿然：高峻独立的样子。像高山一样挺立着一动不动。形容高大坚固，不能动摇。","label":3,"words":"岿然不动"},{"choose":["凌","绫","棱","陵"],"answer":"棱","pinyin":"léng jiǎo fēn míng","id":10,"discrimination":"léng：（棱）角分明\nlíng：（凌）霄\n（绫）罗绸缎\n（陵）墓","title":"()角分明","source":"2015桂林、2014玉林、2014防城港","explanation":"指在一个正方体上棱和角分辨得很清楚。形容两个事物分辨得很清楚或是把人物刻画得很清楚、明了。","label":2,"words":"棱角分明"},{"choose":["琳","林","淋","鳞"],"answer":"淋","pinyin":"kāng kǎi lín lí","id":11,"discrimination":"lín：慷慨（淋）漓\n（琳）琅\n树（林）","title":"慷慨()漓","source":"2016梧州","explanation":"淋漓：充盛，畅快。形容说话、写文章意气昂扬，言辞畅快。","label":4,"words":"慷慨淋漓"},{"choose":["幼","幻","约","焕"],"answer":"幻","pinyin":"mèng huàn","id":12,"discrimination":"huàn：梦（幻）\nyòu：（幼）稚\nyuē：预（约）","title":"梦()","source":"2015贺州","explanation":"梦中的幻境。","label":2,"words":"梦幻"},{"choose":["莹","萤","荧","萦"],"answer":"莹","pinyin":"jīng yíng","id":13,"discrimination":"yíng：晶（莹）\n（萤）火虫\n（荧）光\n（萦）绕","title":"晶()","source":"2017桂林、2015贺州","explanation":"明亮澄澈。","label":3,"words":"晶莹"},{"choose":["拘","叩","叨","佝"],"answer":"叩","pinyin":"kòu mén","id":14,"discrimination":"kòu：（叩）门\njū：（拘）谨\ntāo：（叨）扰\ngōu：（佝）偻","title":"()门","source":"2016贺州","explanation":"敲门。","label":3,"words":"叩门"},{"choose":["令","今","苓","玲"],"answer":"令","pinyin":"qiǎo yán lìng sè","id":15,"discrimination":"lìng：巧言（令）色\njīn：（今）生\nlíng：茯（苓）\n（玲）珑","title":"巧言()色","source":"2014桂林","explanation":"巧言：花言巧语；令色：讨好的表情。形容花言巧语，虚伪讨好。","label":2,"words":"巧言令色"},{"choose":["妄","妾","枉","佞"],"answer":"妄","pinyin":"qīng jǔ wàng dòng","id":16,"discrimination":"wàng：轻举（妄）动\nqiè：（妾）身\nnìng：（佞）臣","title":"轻举()动","source":"2016河池","explanation":"轻：轻率；妄：任意。指不经慎重考虑，轻率地采取行动。","label":2,"words":"轻举妄动"},{"choose":["世","市","式","室"],"answer":"世","pinyin":"jǔ shì wú shuāng","id":17,"discrimination":"shì：举（世）无双\n（市）场\n公（式）\n（室）内","title":"举()无双","source":"2014南宁","explanation":"全世界找不到第二个。形容十分稀有。","label":1,"words":"举世无双"},{"choose":["肄","肆","嗣","津"],"answer":"肆","pinyin":"sì yì","id":18,"discrimination":"sì：（肆）意\nyì：（肄）业\njīn：（津）（津）有味","title":"()意","source":"2015桂林","explanation":"任性；任意。","label":2,"words":"肆意"},{"choose":["榕","溶","容","熔"],"answer":"熔","pinyin":"róng yú yī lú","id":19,"discrimination":"róng：（熔）于一炉\n（榕）树\n（溶）液\n（容）易","title":"()于一炉","source":"2016贺州","explanation":"熔化在同一个炉内。比喻多种事物相互间结合紧密，浑然一体，难分难解。","label":4,"words":"熔于一炉"},{"choose":["声","升","生","笙"],"answer":"生","pinyin":"bié kāi shēng miàn","id":20,"discrimination":"shēng：别开（生）面\n（声）音\n（升）级\n（笙）篁","title":"别开()面","source":"2014崇左","explanation":"生面：新的面目。原意是凌烟阁里的功臣画像本已褪色，经曹将军重画之后才显得有生气。比喻另外创出一种新的形式或局面。","label":1,"words":"别开生面"},{"choose":["圣","胜","剩","盛"],"answer":"胜","pinyin":"yǐn rén rù shèng","id":1,"discrimination":"shèng：引人入（胜）\n（剩）余\n茂（盛）\n（圣）经","title":"引人入()","source":"2014玉林、2014防城港","explanation":"胜：胜境。引人进入佳境。现多用来指风景或文艺作品特别吸引人。","label":1,"words":"引人入胜"},{"choose":["勒","乐","肋","烁"],"answer":"乐","pinyin":"lè bù kě zhī","id":2,"discrimination":"lè：（乐）不可支\nlēi：（勒）紧\nlèi：（肋）骨\nshuò：闪（烁）","title":"()不可支","source":"2016北海","explanation":"支：支撑。快乐到不能撑持的地步。形容欣喜到极点。","label":3,"words":"乐不可支"},{"choose":["市市","事事","式式","是是"],"answer":"事事","pinyin":"wú suǒ shì shì","id":3,"discrimination":"shì：无所（事）事\n（市）场\n公（式）\n莫衷一（是）","title":"无所()()","source":"2015河池","explanation":"是形容闲着什么事情都不干。事事：做事。","label":1,"words":"无所事事"},{"choose":["适","室","示","恃"],"answer":"适","pinyin":"shì kě ér zhǐ","id":4,"discrimination":"shì：（适）可而止\n（室）内\n展（示）\n有（恃）无恐","title":"()可而止","source":"2015桂林","explanation":"适可：恰好可以。到适当的程度就停下来，不要过头。","label":1,"words":"适可而止"},{"choose":["敞","昌","畅","唱"],"answer":"畅","pinyin":"shū chàng","id":5,"discrimination":"chàng：舒（畅）（唱）歌\nchǎng：宽（敞）\nchāng：繁荣（昌）盛","title":"舒()","source":"2016崇左","explanation":"舒畅安适。","label":3,"words":"舒畅"},{"choose":["谩","曼","蔓","慢"],"answer":"谩","pinyin":"màn mà","id":6,"discrimination":"màn：（谩）骂\n轻歌（曼）舞\n（蔓）延\n缓（慢）","title":"()骂","source":"2016桂林","explanation":"肆意乱骂。","label":4,"words":"谩骂"},{"choose":["曼","漫","蔓","慢"],"answer":"蔓","pinyin":"téng wàn","id":7,"discrimination":"wàn：藤（蔓）\nmàn：轻歌（曼）舞\n（漫）不经心\n（慢）吞吞","title":"藤()","source":"2017桂林、2014玉林、2014防城港","explanation":"藤本植物，根生于土壤中的一种易弯或柔软的木本或草本的攀缘植物。","label":2,"words":"藤蔓"},{"choose":["辩","瓣","辨","辫"],"answer":"辩","pinyin":"biàn bó","id":8,"discrimination":"biàn：（辩）驳\n（辨）别\n（辫）子\nbàn：花（瓣）","title":"()驳","source":"2016北海","explanation":"提出理由或根据来反驳对方的意见。","label":2,"words":"辩驳"},{"choose":["炫","渲","喧","眩"],"answer":"眩","pinyin":"tóu yūn mù xuàn","id":9,"discrimination":"xuàn：头晕目（眩）\n（炫）耀\n（渲）染","title":"头晕目()","source":"2016梧州、2014河池","explanation":"头晕眼花，感到一切都在旋转；有时也形容被繁琐的事情弄得不知所措。","label":1,"words":"头晕目眩"},{"choose":["谰","澜","阑","斓"],"answer":"谰","pinyin":"lán yǔ","id":10,"discrimination":"lán：（谰）语\n波（澜）\n灯火（阑）珊\n斑（斓）","title":"()语","source":"2015崇左、2014贵港、2014来宾","explanation":"妄语。","label":4,"words":"谰语"},{"choose":["顾","故","固","雇"],"answer":"故","pinyin":"wēn gù zhī xīn","id":11,"discrimination":"gù：温（故）知新\n（顾）问\n（固）定\n（雇）佣","title":"温()知新","source":"2017广西北部湾经济区四市同城","explanation":"温习学过的知识，而得到新的理解和心得。也指回顾历史，对现在有新的指导意义。","label":1,"words":"温故知新"},{"choose":["怅","倡","畅","唱"],"answer":"畅","pinyin":"chàng xiǎng","id":12,"discrimination":"chàng：（畅）想\n（怅）然\n（倡）导\n（唱）歌","title":"()想","source":"2015玉林、2015防城港","explanation":"无拘无束地尽情想象。","label":1,"words":"畅想"},{"choose":["泻","卸","泄","谢"],"answer":"泄","pinyin":"shuǐ xiè bù tōng","id":13,"discrimination":"xiè：水（泄）不通\n腹（泻）\n推（卸）\n（谢）幕","title":"水()不通","source":"2016桂林","explanation":"泄：排泄。像是连水也流不出去。形容拥挤或包围的非常严密。","label":1,"words":"水泄不通"},{"choose":["居","据","踞","鞠"],"answer":"踞","pinyin":"lóng pán hǔ jù","id":14,"discrimination":"jù：龙盘虎（踞）\n证（据）\njū：（居）住","title":"龙盘虎()","source":"2016北海","explanation":"形容地势雄伟险要。","label":2,"words":"龙盘虎踞"},{"choose":["荣荣","戎戎","溶溶","融融"],"answer":"融融","pinyin":"róng róng xiè xiè","id":15,"discrimination":"róng：（融）（融）泄泄\n（荣）耀\n（戎）装\n（溶）液","title":"()()泄泄","source":"2016河池","explanation":"形容和乐舒畅。","label":1,"words":"融融泄泄"},{"choose":["恹恹","厌厌","淹淹","奄奄"],"answer":"奄奄","pinyin":"qì xī yǎn yǎn","id":16,"discrimination":"yǎn：气息（奄）（奄）\nyān：病（恹）（恹）\n（淹）死\nyàn：（厌）恶","title":"气息()()","source":"2014梧州","explanation":"形容呼吸微弱，快要断气的样子。也比喻事物衰败没落，即将灭亡。","label":3,"words":"气息奄奄"},{"choose":["包","苞","胞","饱"],"answer":"苞","pinyin":"hán bāo yù fàng","id":17,"discrimination":"bāo：含（苞）欲放（包）装\n细（胞）\nbǎo：吃（饱）","title":"含()欲放","source":"2016钦州","explanation":"形容花苞还在叶片里，很快就要开放出来，常用来形容少女。","label":2,"words":"含苞欲放"},{"choose":["咫","帜","织","值"],"answer":"咫","pinyin":"zhǐ chǐ","id":18,"discrimination":"zhǐ：（咫）尺\nzhì：旗（帜）\nzhī：编（织）","title":"()尺","source":"2017桂林、2015百色","explanation":"形容距离近。也指微小，仿佛对方就在眼前。","label":2,"words":"咫尺"},{"choose":["爱爱","艾艾","碍碍","暧暧"],"answer":"艾艾","pinyin":"qī qī ài ài","id":19,"discrimination":"ài：期期（艾）（艾）\n（爱）护\n阻（碍）\n（暧）昧","title":"期期()()","source":"2014来宾","explanation":"形容口吃的人吐辞重复，说话不流利。","label":1,"words":"期期艾艾"},{"choose":["鸣","明","瞑","名"],"answer":"名","pinyin":"dà míng dǐng dǐng","id":20,"discrimination":"míng：大（名）鼎鼎\n（鸣）叫\n（明）天\n（瞑）目","title":"大()鼎鼎","source":"2017河池、2015北海","explanation":"形容名气很大，极其有名。","label":1,"words":"大名鼎鼎"},{"choose":["偏偏","篇篇","扁扁","翩翩"],"answer":"翩翩","pinyin":"piān piān qǐ wǔ","id":1,"discrimination":"piān：（翩）（翩）起舞\n（偏）爱\n（篇）章\n（扁）舟","title":"()()起舞","source":"2014桂林","explanation":"形容轻快地跳起舞来。","label":4,"words":"翩翩起舞"},{"choose":["黄","簧","横","衡"],"answer":"横","pinyin":"héng kōng chū shì","id":2,"discrimination":"héng：（横）空出世\nhuáng：枯（黄）\n弹（簧）","title":"()空出世","source":"2014玉林、2014防城港","explanation":"形容人或物高大，横在空中，浮出人世，或比喻卓尔不群。","label":2,"words":"横空出世"},{"choose":["拖","迤","脱","施"],"answer":"拖","pinyin":"tuō ní dài shuǐ","id":3,"discrimination":"tuō：（拖）泥带水\nyǐ：（迤）逦\nshī：（施）工","title":"()泥带水","source":"2016百色","explanation":"比喻说话、写文章不简洁或做事不干脆。","label":2,"words":"拖泥带水"},{"choose":["扉","非","菲","匪"],"answer":"扉","pinyin":"fēi yè","id":4,"discrimination":"fēi：（扉）页\n（非）凡\nfěi：不（菲）\n土（匪）","title":"()页","source":"2014贵港","explanation":"也叫内封。书籍正文前载有书名、编著者姓名、出版社名称等的一页。","label":2,"words":"扉页"},{"choose":["候","侯","喉","后"],"answer":"候","pinyin":"děng hòu","id":5,"discrimination":"hòu：等（候）\nhóu：（侯）爵\n（喉）咙","title":"等()","source":"2015钦州","explanation":"一般用作静候某个时机的出现。","label":2,"words":"等候"},{"choose":["承","诚","成","城"],"answer":"诚","pinyin":"chéng yì","id":6,"discrimination":"chéng：（诚）意\n（承）认\n（成）功\n（城）墙","title":"()意","source":"2017梧州","explanation":"真心。","label":1,"words":"诚意"},{"choose":["璧","避","壁","碧"],"answer":"碧","pinyin":"bì yù","id":7,"discrimination":"bì：（碧）玉\n完（璧）归赵\n躲（避）\n墙（壁）","title":"()玉","source":"2016贺州","explanation":"一种不透明隐晶质石英，常见有几种颜色(如红色、褐色、绿色、黄色）","label":4,"words":"碧玉"},{"choose":["癜","癫","巅","滇"],"answer":"巅","pinyin":"shān diān","id":8,"discrimination":"diān：山（巅）\n（癫）狂\n（滇）池\ndiàn：白（癜）风","title":"山()","source":"2014玉林、2014防城港","explanation":"山顶。","label":3,"words":"山巅"},{"choose":["姹","宅","诧","咤"],"answer":"诧","pinyin":"jīng chà","id":9,"discrimination":"chà：惊（诧）\n（姹）紫嫣红\nzhái：（宅）门\nzhà：叱（咤）风云","title":"惊()","source":"2014贺州","explanation":"惊讶诧异。","label":2,"words":"惊诧"},{"choose":["义","异","益","逸"],"answer":"逸","pinyin":"yī láo yǒng yì","id":10,"discrimination":"yì：一劳永（逸）\n仗（义）\n奇（异）\n多多（益）善","title":"一劳永()","source":"2016桂林","explanation":"逸：安逸。辛苦一次，把事情办好，以后就可以不再费力了。","label":1,"words":"一劳永逸"},{"choose":["勃","脖","悖","蓓"],"answer":"悖","pinyin":"bèi miù","id":11,"discrimination":"bèi：（悖）谬\nbó：（勃）然大怒（脖）子","title":"()谬","source":"2016桂林","explanation":"不合道理。也作背谬。","label":2,"words":"悖谬"},{"choose":["妆","壮","装","状"],"answer":"壮","pinyin":"lǐ zhí qì zhuàng","id":12,"discrimination":"zhuàng：理直气（壮）\n（状）态\nzhuāng：化（妆）","title":"理直气()","source":"2016贺州","explanation":"理由充分、因而说话有气势。","label":2,"words":"理直气壮"},{"choose":["虹","宏","红","鸿"],"answer":"红","pinyin":"wàn zǐ qiān hóng","id":13,"discrimination":"hóng：万紫千（红）\n彩（虹）\n（宏）伟\n（鸿）毛","title":"万紫千()","source":"2014玉林、2014防城港","explanation":"形容百花齐放，色彩艳丽。多指繁盛的春色，也比喻事物丰富多彩。","label":1,"words":"万紫千红"},{"choose":["更更","耿耿","狄狄","梗梗"],"answer":"耿耿","pinyin":"gěng gěng yú huái","id":14,"discrimination":"gěng：（耿）（耿）于怀\n桔（梗）\ngèng：（更）加\ndí ：戎（狄）","title":"()()于怀","source":"2015桂林","explanation":"形容令人牵挂或不愉快的事在心里难以排解。","label":3,"words":"耿耿于怀"},{"choose":["尔","而","耳","迩"],"answer":"尔","pinyin":"wēn wén ěr yǎ","id":15,"discrimination":"ěr：温文（尔）雅\n（而）且\n（耳）朵\n遐（迩）","title":"温文()雅","source":"2014桂林","explanation":"形容人态度温和，举动斯文。","label":1,"words":"温文尔雅"},{"choose":["诺","匿","偌","若"],"answer":"诺","pinyin":"chéng nuò","id":16,"discrimination":"nuò：承（诺）\nnì：（匿）名\nruò：（偌）大\n（若）有（若）无","title":"承()","source":"2014钦州","explanation":"1.答应做某事。2.法律上指受要约人同意要约的意思表示。应以通知的方式作出，但根据交易习惯或要约表明可通过行为作出的除外。该通知到达要约人时生效，合同成立。与“要约”相对。","label":2,"words":"承诺"},{"choose":["逸","意","益","义"],"answer":"逸","pinyin":"xián qíng yì zhì","id":17,"discrimination":"yì：闲情（逸）致\n（意）愿\n（益）处\n仗（义）","title":"闲情()致","source":"2014梧州","explanation":"悠闲的心情和安逸的兴致。","label":1,"words":"闲情逸致"},{"choose":["嘱","属","署","瞩"],"answer":"瞩","pinyin":"gāo zhān yuǎn zhǔ","id":18,"discrimination":"zhǔ：高瞻远（瞩）\n叮（嘱）\nshǔ：（属）于","title":"高瞻远()","source":"2014河池","explanation":"站得高，看得远。比喻眼光远大。","label":2,"words":"高瞻远瞩"},{"choose":["疾","嫉","级","急"],"answer":"嫉","pinyin":"jí dù","id":19,"discrimination":"jí：（嫉）妒\n（疾）病\n（级）别\n（急）忙","title":"()妒","source":"2014钦州","explanation":"因人胜过自己而产生的忌恨心理。","label":1,"words":"嫉妒"},{"choose":["题","提","剃","蹄"],"answer":"提","pinyin":"pú tí shù","id":20,"discrimination":"tí：菩（提）树\n答（题）\n马（蹄）\ntì：（剃）头","title":"菩()树","source":"2014钦州","explanation":"常绿乔木，叶子卵圆形，前端细长，花托略作球形，花隐藏在花托内，果实扁圆形。从树干中取出的乳状汁液可制硬树胶。原产印度，相传释迦牟尼曾坐菩提树下顿悟佛理，所以菩提树被佛教称为圣树。","label":3,"words":"菩提树"},{"choose":["直","值","执","植"],"answer":"直","pinyin":"yǒng wǎng zhí qián","id":1,"discrimination":"zhí：勇往（直）前\n（值）班\n（植）物","title":"勇往()前","source":"2015梧州、2014南宁","explanation":"勇敢地一直向前进。","label":4,"words":"勇往直前"},{"choose":["奥","懊","澳","墺"],"answer":"奥","pinyin":"shēn ào","id":2,"discrimination":"ào：深（奥）\n（懊）悔\n（澳）门\n深山野（墺）","title":"深()","source":"2017河池","explanation":"（道理、含义）高深、不易理解。","label":4,"words":"深奥"},{"choose":["晤","悟","吾","梧"],"answer":"晤","pinyin":"huì wù","id":3,"discrimination":"wù：会（晤）\n醒（悟）\nwú：三省（吾）身\n（梧）桐","title":"会()","source":"2015北海","explanation":"会面；见面。","label":2,"words":"会晤"},{"choose":["振","震","赈","阵"],"answer":"赈","pinyin":"zhèn  zāi","id":4,"discrimination":"zhèn：（赈）灾\n（振）作\n地（震）\n（阵）地","title":"()灾","source":"2014百色","explanation":"赈济灾民。","label":1,"words":"赈灾"},{"choose":["徕","睐","赖","莱"],"answer":"徕","pinyin":"zhāo lái","id":5,"discrimination":"lái：招（徕）\n蓬（莱）\nlài：青（睐）","title":"招()","source":"2015百色","explanation":"招引（多指把顾客招来）。","label":2,"words":"招徕"},{"choose":["采","彩","踩","睬"],"answer":"彩","pinyin":"duō zī duō cǎi","id":6,"discrimination":"cǎi：多姿多（彩）\n（采）摘\n（踩）踏\n理（睬）","title":"多姿多()","source":"2015南宁","explanation":"指丰富多彩，形容颜色形态多样，很多种形状，很多种颜色。","label":4,"words":"多姿多彩"},{"choose":["涉","慑","摄","赦"],"answer":"涉","pinyin":"shè jí","id":7,"discrimination":"shè：（涉）及\n（慑）惧\n（摄）影\n（赦）免","title":"()及","source":"2015贺州","explanation":"指关联到，牵涉到。","label":1,"words":"涉及"},{"choose":["湛","勘","甚","瞰"],"answer":"湛","pinyin":"shēn zhàn","id":8,"discrimination":"zhàn：深（湛）\nkān：（勘）察\nshèn：（甚）至","title":"深()","source":"2015玉林、2015防城港","explanation":"指精深；深厚。","label":2,"words":"深湛"},{"choose":["辜","箍","估","顾"],"answer":"辜","pinyin":"wú gū","id":9,"discrimination":"gū：无（辜）\n紧（箍）咒\n（估）计\ngù：左（顾）右盼","title":"无()","source":"2014钦州","explanation":"指没有罪；没有做错。","label":3,"words":"无辜"},{"choose":["弛","地","池","驰"],"answer":"驰","pinyin":"chí míng","id":10,"discrimination":"chí：（驰）名\n松（弛）\n（池）塘\ndì：（地）球","title":"()名","source":"2016钦州","explanation":"指声名传的很远。","label":2,"words":"驰名"},{"choose":["像","向","象","巷"],"answer":"象","pinyin":"wàn xiàng gēng xīn","id":11,"discrimination":"xiàng：万（象）更新\n好（像）\n方（向）\n（巷）子","title":"万()更新","source":"2017梧州","explanation":"指事物或景象改换了样子，出现了一番新气象。","label":1,"words":"万象更新"},{"choose":["憩","戚","契","棋"],"answer":"憩","pinyin":"xiǎo qì","id":12,"discrimination":"qì：小（憩）\n（契）约\nqī：哀（戚）\nqí：围（棋）","title":"小()","source":"2014贵港","explanation":"指小小的休息一会儿；稍作休息。","label":3,"words":"小憩"},{"choose":["盾","遁","寻","循"],"answer":"循","pinyin":"xún xù jiàn jìn","id":13,"discrimination":"xún：（循）序渐进\ndùn：后（盾）\n（遁）世","title":"()序渐进","source":"2014贺州","explanation":"指学习工作等按照一定的步骤逐渐深入或提高。","label":2,"words":"循序渐进"},{"choose":["箱","相","乡","香"],"answer":"相","pinyin":"yán xíng xiāng gù","id":14,"discrimination":"xiāng：言行（相）顾\n家（乡）\n（香）水\n（箱）子","title":"言行()顾","source":"2015南宁","explanation":"指言行不互相矛盾。","label":1,"words":"言行相顾"},{"choose":["咽","曳","烨","噎"],"answer":"噎","pinyin":"chōu yē","id":15,"discrimination":"yē：抽（噎）\nyè：拖（曳）\n（烨）烁\n哽（咽）","title":"抽()","source":"2016崇左","explanation":"指一吸一顿地哭泣，啜泣。","label":3,"words":"抽噎"},{"choose":["诣","指","旨","谐"],"answer":"诣","pinyin":"zào yì","id":16,"discrimination":"yì：造（诣）\nzhǐ：（指）控\n圣（旨）\nxié：和（谐）","title":"造()","source":"2017贺州","explanation":"学问、技艺等所达到的水平。","label":2,"words":"造诣"},{"choose":["躬","功","宫","恭"],"answer":"恭","pinyin":"xǐ ěr gōng tīng","id":17,"discrimination":"gōng：洗耳（恭）听\n鞠（躬）\n（功）劳\n（宫）殿","title":"洗耳()听","source":"2016南宁","explanation":"指做好准备用心地聆听别人说的话，对自己有很大的帮助。请人讲话时的客气话，指专心地听。","label":1,"words":"洗耳恭听"},{"choose":["摇","谣","瑶","遥"],"answer":"谣","pinyin":"zào yáo shēng shì","id":18,"discrimination":"yáo：造（谣）生事\n（摇）篮\n（瑶）池\n逍（遥）","title":"造()生事","source":"2017河池、2015桂林","explanation":"制造谣言，挑起事端。","label":4,"words":"造谣生事"},{"choose":["谢","卸","泻","泄"],"answer":"泄","pinyin":"xiè qì","id":19,"discrimination":"xiè：（泄）气\n感（谢）\n推（卸）\n腹（泻）","title":"()气","source":"2014百色","explanation":"1.泄劲。2.讥讽低劣或没有本领。","label":1,"words":"泄气"},{"choose":["侧","测","恻","厕"],"answer":"恻","pinyin":"cè yǐn","id":20,"discrimination":"cè：（恻）隐\n（侧）面\n（测）量\n（厕）所","title":"()隐","source":"2014来宾、2014贵港","explanation":"对受苦难的人表示同情；不忍。","label":4,"words":"恻隐"},{"choose":["沛","佩","配","霈"],"answer":"沛","pinyin":"diān pèi","id":1,"discrimination":"pèi：颠（沛）\n（佩）服\n（配）备\n甘（霈）","title":"颠()","source":"2016崇左","explanation":"困苦，受挫折。","label":1,"words":"颠沛"},{"choose":["副","幅","福","辐"],"answer":"幅","pinyin":"fú yuán","id":2,"discrimination":"fú：（幅）员\n（福）气\n（辐）射\nfù：（副）本","title":"()员","source":"2017桂林","explanation":"领土面积（幅：宽度；员：周围）。","label":2,"words":"幅员"},{"choose":["轮","纶","抡","伦"],"answer":"伦","pinyin":"jué lún","id":3,"discrimination":"lún：绝（伦）\n车（轮）\n垂（纶）\n（抡）锤","title":"绝()","source":"2015贺州","explanation":"无论谁或任何事物都比不上。","label":4,"words":"绝伦"},{"choose":["康","糠","抗","慷"],"answer":"慷","pinyin":"kāng kǎi","id":4,"discrimination":"kāng：（慷）慨\n安（康）\n糟（糠）","title":"()慨","source":"2014桂林、2014南宁","explanation":"1.充满正气，情绪激昂。2.不吝惜。","label":4,"words":"慷慨"},{"choose":["阑","斓","澜","谰"],"answer":"阑","pinyin":"lán shān","id":5,"discrimination":"lán：（阑）珊\n斑（斓）\n波（澜）\n（谰）言","title":"()珊","source":"2014玉林、2014防城港","explanation":"将尽；衰落。","label":4,"words":"阑珊"},{"choose":["稂","郎","琅","踉"],"answer":"踉","pinyin":"liàng qiàng","id":6,"discrimination":"liàng：（踉）跄\nláng：（稂）莠不齐\n（郎）中\n琳（琅）","title":"()跄","source":"2014贵港","explanation":"走路不稳。","label":2,"words":"踉跄"},{"choose":["昧","寐","袂","魅"],"answer":"寐","pinyin":"mèng mèi","id":7,"discrimination":"mèi：梦（寐）\n冒（昧）\n联（袂）\n（魅）力","title":"梦()","source":"2014百色","explanation":"睡梦。","label":1,"words":"梦寐"},{"choose":["涂","徐","途","图"],"answer":"途","pinyin":"dào tīng tú shuō","id":8,"discrimination":"tú：道听（途）说\n（涂）抹\nxú：清风（徐）来","title":"道听()说","source":"2014钦州","explanation":"道、途：路。路上听来的、路上传播的话。泛指没有根据的传闻。","label":2,"words":"道听途说"},{"choose":["倪","旎","霓","溺"],"answer":"霓","pinyin":"ní hóng dēng","id":9,"discrimination":"ní：（霓）虹灯\n端（倪）\nnǐ：旖（旎）\nnì：沉（溺）","title":"()虹灯","source":"2014钦州","explanation":"灯的一种，在真空中玻璃管内充入氖，两端安装电极，通电后发出红色或蓝色的光。多用做广告灯或信号灯。","label":3,"words":"霓虹灯"},{"choose":["剥","渤","帛","驳"],"answer":"驳","pinyin":"biàn bó","id":10,"discrimination":"bó：辩（驳）\n（渤）海\n（帛）画\nbō：（剥）削","title":"辩()","source":"2016北海","explanation":"提出理由或根据来反驳对方的意见。","label":3,"words":"辩驳"},{"choose":["叠","跌","迭","秩"],"answer":"迭","pinyin":"xiǎn xiàng dié shēng","id":11,"discrimination":"dié：险象（迭）生\ndiē：（跌）落\nzhì：（秩）序","title":"险象()生","source":"2014梧州","explanation":"接二连三地发生危险。比喻途中的危险很多。","label":2,"words":"险象迭生"},{"choose":["娇","矫","骄","轿"],"answer":"矫","pinyin":"jiǎo jiàn","id":12,"discrimination":"jiǎo：（矫）健\njiāo：（娇）气\n（骄）傲\njiào：花（轿）","title":"()健","source":"2016柳州","explanation":"指强壮健力，英勇威武。","label":2,"words":"矫健"},{"choose":["袤","矛","茅","茂"],"answer":"袤","pinyin":"guǎng mào wú yín","id":13,"discrimination":"mào：广（袤）无垠\n风华正（茂）\nmáo：（矛）盾\n名列前（茅）","title":"广()无垠","source":"2014来宾","explanation":"广：东西的长度。袤：南北的长度。垠：边际；边界。形容广阔得望不到边际，辽阔无边。比喻非常广阔。","label":3,"words":"广袤无垠"},{"choose":["隘","溢","缢","益"],"answer":"隘","pinyin":"ài kǒu","id":14,"discrimination":"ài：（隘）口\nyì：洋（溢）\n自（缢）\n受（益）","title":"()口","source":"2016桂林","explanation":"隘口，指狭隘的山路口。出自清代蒲松龄 《聊斋志异·崔猛》：“马恋驹奔驶，申从之。出一隘口，申灼火於绳，徧悬之，乃归。”","label":2,"words":"隘口"},{"choose":["肃","素","宿","夙"],"answer":"素","pinyin":"ān zhī ruò sù","id":15,"discrimination":"sù：安之若（素）\n严（肃）\n住（宿）\n（夙）愿","title":"安之若()","source":"2015玉林、防城港","explanation":"安：安然，坦然；之：代词，指人或物；素：平常。安然相处，和往常一样，不觉得有什么不合适。","label":1,"words":"安之若素"},{"choose":["岸","黯","案","按"],"answer":"按","pinyin":"àn bù jiù bān","id":16,"discrimination":"àn：（按）部就班\n海（岸）\n（黯）然失色\n档（案）","title":"()部就班","source":"2016北海","explanation":"按照一定的条理，遵循一定的程序。也指按老规矩办事，缺乏创新精神。","label":1,"words":"按部就班"},{"choose":["喑","黯","暗","谙"],"answer":"黯","pinyin":"àn rán shī sè","id":17,"discrimination":"àn：（黯）然失色\n（暗）无天日\nyīn：（喑）哑\nān：不（谙）世事","title":"()然失色","source":"2014崇左、2015梧州、2017贺州","explanation":"黯然：心里不舒服、情绪低落的样子；失色：因惊恐而变以脸色。本指心情不好，脸色难看。后多比喻相形之下很有差距，远远不如。","label":2,"words":"黯然失色"},{"choose":["懊","墺","奥","澳"],"answer":"奥","pinyin":"ào mì","id":18,"discrimination":"ào：（奥）秘\n（懊）恼\n深山野（墺）\n（澳）门","title":"()秘","source":"2015来宾","explanation":"深奥的尚未被认识的秘密。","label":4,"words":"奥秘"},{"choose":["奥","墺","懊","澳"],"answer":"懊","pinyin":"ào huǐ","id":19,"discrimination":"ào：（懊）悔\n（奥）秘\n深山野（墺）\n（澳）门","title":"()悔","source":"2016百色","explanation":"做错了事或说错了话，心里自恨不该这样。","label":4,"words":"懊悔"},{"choose":["隙","溪","希","惜"],"answer":"隙","pinyin":"bái jū guò xì","id":20,"discrimination":"xì：白驹过（隙）\nxī：（溪）水\n（希）冀\n珍（惜）","title":"白驹过()","source":"2016钦州","explanation":"比喻时间过得快，光阴易逝。","label":3,"words":"白驹过隙"},{"choose":["斓","澜","阑","谰"],"answer":"斓","pinyin":"bān lán","id":1,"discrimination":"lán：斑（斓）\n波（澜）\n灯火（阑）珊\n（谰）言","title":"斑()","source":"2014玉林、防城港","explanation":"灿烂多彩。","label":4,"words":"斑斓"},{"choose":["悯","闵","闽","泯"],"answer":"悯","pinyin":"bēi tiān mǐn rén","id":2,"discrimination":"mǐn：悲天（悯）人\n姓（闵）\n（闽）南\n（泯）灭","title":"悲天()人","source":"2014河池","explanation":"悲天：哀叹时世；悯人：怜惜众人。指哀叹时世的艰难，怜惜人们的痛苦。","label":1,"words":"悲天悯人"},{"choose":["茁","绌","拙","础"],"answer":"拙","pinyin":"bèn zhuō","id":3,"discrimination":"zhuō：笨（拙）\nzhuó：（茁）壮\nchù：相形见（绌）\nchǔ：基（础）","title":"笨()","source":"2016桂林","explanation":"笨；不聪明；不灵巧。","label":2,"words":"笨拙"},{"choose":["姨","胰","夷","痍"],"answer":"夷","pinyin":"bǐ yí","id":4,"discrimination":"yí：鄙（夷）\n阿（姨）\n（胰）腺\n疮（痍）","title":"鄙()","source":"2017贺州","explanation":"指轻视，看不起。出自唐·韩愈《柳州罗池庙碑》：“柳侯为州，不鄙夷其民，动以礼治。”","label":4,"words":"鄙夷"},{"choose":["梗","羹","庚","更"],"answer":"羹","pinyin":"bì mén gēng","id":5,"discrimination":"gēng：闭门（羹）\n（庚）帖\ngěng：桔（梗）\ngèng：（更）加","title":"闭门()","source":"2014钦州","explanation":"指主人拒绝客人进门叫做让客人吃闭门羹。","label":3,"words":"闭门羹"},{"choose":["彬彬","杉杉","滨滨","宾宾"],"answer":"彬彬","pinyin":"bīn bīn yǒu lǐ","id":6,"discrimination":"bīn：（彬）（彬）有礼\n海（滨）\n（宾）客\nshān：银（杉）","title":"()()有礼","source":"2015河池","explanation":"彬彬：原意为文质兼备的样子，后形容文雅。形容文雅有礼貌的样子。","label":3,"words":"彬彬有礼"},{"choose":["慌","荒","谎","梳"],"answer":"荒","pinyin":"bīng huāng mǎ luàn","id":7,"discrimination":"huāng：兵（荒）马乱\n（慌）张\nhuǎng：（谎）话\nshū：（梳）子","title":"兵()马乱","source":"2015桂林","explanation":"荒、乱：指社会秩序不安定。形容战争期间社会混乱不安的景象。","label":2,"words":"兵荒马乱"},{"choose":["傅","缚","搏","博"],"answer":"博","pinyin":"bó xué","id":8,"discrimination":"bó：（博）学\n脉（搏）\nfù：（傅）彩\n束（缚）","title":"()学","source":"2015南宁","explanation":"学识渊博，知道的多，了解的广，知识丰富。","label":2,"words":"博学"},{"choose":["名","明","瞑","铭"],"answer":"名","pinyin":"bù kě míng zhuàng","id":9,"discrimination":"míng：不可（名）状\n（明）亮\n（瞑）目\n（铭）记","title":"不可()状","source":"2015河池、2015北海","explanation":"无法用语言来形容。名：说出。状：描述。语出《老子》第十四章：“绳绳不可名，复归于无物，是谓无状之状，无物之象。”","label":1,"words":"不可名状"},{"choose":["质","置","智","制"],"answer":"置","pinyin":"bù róng zhì yí","id":10,"discrimination":"zhì：不容（置）疑\n（质）量\n（智）慧\n（制）造","title":"不容()疑","source":"2016百色","explanation":"不允许有什么怀疑。表示论证严密，无可怀疑。出自宋·陆游《严州乌龙广济庙碑》：“盖其灵响暴著，亦有不容置疑者矣。”","label":1,"words":"不容置疑"},{"choose":["辨","辫","瓣","辩"],"answer":"辩","pinyin":"bù xiè zhì biàn","id":11,"discrimination":"biàn：不屑置（辩）\n（辨）别\n（辫）子\nbàn：花（瓣）","title":"不屑置()","source":"2014百色","explanation":"认为不值得分辩。","label":2,"words":"不屑置辩"},{"choose":["逾","俞","喻","愈"],"answer":"喻","pinyin":"bù yán ér yù","id":12,"discrimination":"yù：不言而（喻）\n痊（愈）\nyú：（逾）越\n（俞）允","title":"不言而()","source":"2015玉林、防城港、2016桂林、2015梧州","explanation":"喻：了解，明白。形容道理很明显。","label":2,"words":"不言而喻"},{"choose":["燃","蚺","髯","然"],"answer":"然","pinyin":"bù yǐ wéi rán","id":13,"discrimination":"rán：不以为（然）\n点（燃）\n（蚺）胆\n虬（髯）","title":"不以为()","source":"2016崇左","explanation":"然：是，对。不认为是对的。表示不同意或否定。","label":1,"words":"不以为然"},{"choose":["输","疏","梳","蔬"],"answer":"疏","pinyin":"cái shū xué qiǎn","id":14,"discrimination":"shū：才（疏）学浅\n（输）赢\n（梳）理\n（蔬）菜","title":"才()学浅","source":"2017桂林、2014河池","explanation":"疏：浅薄。才学不高，学识不深（多用作自谦的话）。出自《汉书·谷永传》：“臣才朽学浅，不通政事。”","label":1,"words":"才疏学浅"},{"choose":["渗","掺","参","叁"],"answer":"掺","pinyin":"chān zá","id":15,"discrimination":"chān：（掺）杂\nshèn：（渗）透\ncān：（参）加\nsān：（叁）天两地","title":"()杂","source":"2014贵港","explanation":"掺杂是指多种物质混杂在一起。","label":2,"words":"掺杂"},{"choose":["擅","颤","膻","嬗"],"answer":"颤","pinyin":"chàn dǒu","id":16,"discrimination":"chàn：（颤）抖\nshàn：（擅）长\n（嬗）变\nshān：腥（膻）","title":"()抖","source":"2017贺州","explanation":"指颤动；哆嗦。形容身体某个部位发抖。","label":2,"words":"颤抖"},{"choose":["尘","沉","辰","陈"],"answer":"陈","pinyin":"chén cí làn diào","id":17,"discrimination":"chén：（陈）词滥调\n（尘）土\n（沉）默\n星（辰）","title":"()词滥调","source":"2016贺州","explanation":"陈：陈旧，陈腐；滥：浮泛不合实际。指陈腐、空泛的论调。","label":1,"words":"陈词滥调"},{"choose":["淅","晰","晞","曦"],"answer":"曦","pinyin":"chén xī","id":18,"discrimination":"xī：晨（曦）\n（淅）沥\n清（晰）\n晨露未（晞）","title":"晨()","source":"2014玉林、防城港、2015桂林、2014河池","explanation":"清晨的阳光，象征温暖、光明。","label":3,"words":"晨曦"},{"choose":["呈","承","成","城"],"answer":"承","pinyin":"chéng qián qǐ hòu","id":19,"discrimination":"chéng：（承）前启后\n（呈）现\n马到（成）功\n（城）市","title":"()前启后","source":"2015贺州","explanation":"继承前面的，开创后来的。指继承前人事业，为后人开辟道路。承：承接；启：开创、开始。","label":1,"words":"承前启后"},{"choose":["呈","成","承","城"],"answer":"承","pinyin":"chéng zài","id":20,"discrimination":"chéng：（承）载\n（呈）现\n马到（成）功\n（城）市","title":"()载","source":"2015河池","explanation":"指承受支撑物体。出自唐·孔颖达疏：“以绳束其版，版满筑讫，则升下於上，以相承载，作此宗庙。”","label":1,"words":"承载"},{"choose":["瞪","橙","登","澄"],"answer":"澄","pinyin":"chéng qīng","id":1,"discrimination":"chéng：（澄）清\n（橙）子\ndèng：目（瞪）口呆\ndēng：（登）山","title":"()清","source":"2014桂林","explanation":"指杂质沉淀，液体变清；形容水清而透明。","label":2,"words":"澄清"},{"choose":["充","冲","憧","忡"],"answer":"充","pinyin":"chōng ěr bù wén","id":2,"discrimination":"chōng：（充）耳不闻\n（冲）锋陷阵\n（憧）憬\n忧心（忡）（忡）","title":"()耳不闻","source":"2016崇左、2015河池","explanation":"充：塞住。塞住耳朵不听。形容有意不听别人的意见。","label":1,"words":"充耳不闻"},{"choose":["绸","惆","稠","筹"],"answer":"稠","pinyin":"chóu mì","id":3,"discrimination":"chóu：（稠）密\n（绸）缎\n（惆）怅\n（筹）划","title":"()密","source":"2017柳州、2014贺州","explanation":"指数量多,密度大。与“稀疏”相对。","label":1,"words":"稠密"},{"choose":["著","褚","渚","躇"],"answer":"躇","pinyin":"chóu chú","id":4,"discrimination":"chóu：（踌）躇\nzhù：（著）名\nzhǔ：（褚）幕\n江（渚）","title":"踌()","source":"2016贺州、2014来宾","explanation":"指犹豫不决，拿不定主意。也做思量、考虑的意思。出自宋玉《九辩》：“蹇淹留而踌躇。”","label":3,"words":"踌躇"},{"choose":["触","畜","怵","处"],"answer":"触","pinyin":"chù mù shāng huái","id":5,"discrimination":"chù：（触）目伤怀\n（畜）力\n发（怵）\n到（处）","title":"()目伤怀","source":"2015贺州","explanation":"触目：视线接触到。伤怀：引起伤感的情绪。看到某种情况而内心伤悲。","label":1,"words":"触目伤怀"},{"choose":["疵","呲","龇","泚"],"answer":"疵","pinyin":"chuī máo qiú cī","id":6,"discrimination":"cī：吹毛求（疵）\n挨（呲）儿\nzī：（龇）牙咧嘴\ncǐ：（泚）笔","title":"吹毛求()","source":"2014来宾、2014崇左","explanation":"把皮上的毛吹开，寻找疵点。比喻故意挑毛病找错。","label":2,"words":"吹毛求疵"},{"choose":["炼","练","链","潋"],"answer":"炼","pinyin":"chuí liàn","id":7,"discrimination":"liàn：锤（炼）\n教（练）\n（链）条\n（潋）滟","title":"锤()","source":"2014玉林、防城港","explanation":"1.磨炼。2.刻苦钻研，反复琢磨使艺术等精练、纯熟。","label":1,"words":"锤炼"},{"choose":["萃","粹","悴","淬"],"answer":"粹","pinyin":"chún cuì","id":8,"discrimination":"cuì：纯（粹）\n拔（萃）超群\n憔（悴）\n（淬）火","title":"纯()","source":"2016北海","explanation":"指不掺杂其它成分的；无搀合物的；不含添加、替代或异质物质的。","label":4,"words":"纯粹"},{"choose":["啜","缀","辍","掇"],"answer":"啜","pinyin":"chuò qì","id":9,"discrimination":"chuò：（啜）泣\n（辍）学\nzhuì：点（缀）\nduō：（掇）拾","title":"()泣","source":"2015来宾","explanation":"指抽噎、抽泣，抽抽搭搭地哭。","label":2,"words":"啜泣"},{"choose":["笼","胧","茏","珑"],"answer":"茏","pinyin":"cōng lóng","id":10,"discrimination":"lóng：葱（茏）\n蒸（笼）\n朦（胧）\n八面玲（珑）","title":"葱()","source":"2016北海","explanation":"草木青翠茂盛。","label":4,"words":"葱茏"},{"choose":["滥","槛","蓝","监"],"answer":"滥","pinyin":"cū zhì làn zào","id":11,"discrimination":"làn：粗制（滥）造\nkǎn：门（槛）\nlán：（蓝）天\njiān：（监）狱","title":"粗制()造","source":"2015梧州、2015崇左","explanation":"指制作粗劣，不讲究质量，也指工作不负责任，草率行事。","label":2,"words":"粗制滥造"},{"choose":["萃","瘁","悴","猝"],"answer":"猝","pinyin":"cù bù jí fáng","id":12,"discrimination":"cù：（猝）不及防\ncuì：荟（萃）\n鞠躬尽（瘁）\n憔（悴）","title":"()不及防","source":"2015桂林","explanation":"形容事情来得突然，来不及防备。","label":2,"words":"猝不及防"},{"choose":["簇","蔟","促","蹙"],"answer":"簇","pinyin":"cù xīn","id":13,"discrimination":"cù：（簇）新\n蚕（蔟）\n（促）成\n（蹙）额","title":"()新","source":"2017梧州、2016南宁","explanation":"极新；全新。","label":1,"words":"簇新"},{"choose":["蹿","窜","镩","撺"],"answer":"撺","pinyin":"cuān duo","id":14,"discrimination":"cuān：（撺）掇\n（蹿）动\n（镩）冰\ncuàn：（窜）改","title":"()掇","source":"2014贵港","explanation":"1.在一旁鼓动人做某事。2.催逼；催促。","label":2,"words":"撺掇"},{"choose":["灿","璨","孱","粲"],"answer":"璨","pinyin":"cuǐ càn","id":15,"discrimination":"càn：璀（璨）\n（灿）烂\n（孱）头\n（粲）然","title":"璀()","source":"2015百色","explanation":"形容珠玉等光彩鲜明，非常绚丽。也用于人或事物。","label":1,"words":"璀璨"},{"choose":["砌","沏","彻","切"],"answer":"彻","pinyin":"dà chè dà wù","id":16,"discrimination":"chè：大（彻）大悟\nqì：堆（砌）\nqī：（沏）茶\nqiè：迫（切）","title":"大()大悟","source":"2014南宁","explanation":"彻：通，透；悟：领会。形容彻底觉悟或醒悟。","label":2,"words":"大彻大悟"},{"choose":["廷","庭","亭","霆"],"answer":"庭","pinyin":"dà tíng guǎng zhòng","id":17,"discrimination":"tíng：大（庭）广众\n内（廷）\n（亭）（亭）玉立\n大发雷（霆）","title":"大()广众","source":"2014崇左","explanation":"大庭：宽大的场地；广众：为数很多的人群。指聚集很多人的公开场合。","label":1,"words":"大庭广众"},{"choose":["羡","恙","漾","羌"],"answer":"漾","pinyin":"dàng yàng","id":18,"discrimination":"yàng：荡（漾）\n安然无（恙）\nxiàn：（羡）慕\nqiāng：（羌）笛","title":"荡()","source":"2014河池","explanation":"指飘荡；起伏不定；水面等起伏波动；形容起伏动荡。","label":2,"words":"荡漾"},{"choose":["巅","颠","癫","滇"],"answer":"巅","pinyin":"diān fēng","id":19,"discrimination":"diān：（巅）峰\n（颠）簸\n疯（癫）\n（滇）池","title":"()峰","source":"2015北海","explanation":"巅：山顶。峰： 高而尖的山头。巅峰：事物发展的最高峰。","label":4,"words":"巅峰"},{"choose":["碘","腆","典","觍"],"answer":"典","pinyin":"diǎn fàn","id":20,"discrimination":"diǎn：（典）范\n（碘）盐\ntiǎn：腼（腆）\n（觍）颜","title":"()范","source":"2016河池","explanation":"褒义词，形容某人某事为他人之表率。","label":2,"words":"典范"},{"choose":["碉","凋","绸","惆"],"answer":"凋","pinyin":"diāo líng","id":1,"discrimination":"diāo：（凋）零\n（碉）堡\nchóu：（绸）缎\n（惆）怅","title":"()零","source":"2016百色","explanation":"1.衰败,不振。2.用来比喻人的死伤离散。3.凋谢，零落。","label":2,"words":"凋零"},{"choose":["凋","惆","倜","绸"],"answer":"凋","pinyin":"diāo xiè","id":2,"discrimination":"diāo：（凋）谢\nchóu：（绸）缎\n（惆）怅\ntì：（倜）傥","title":"()谢","source":"2016贺州","explanation":"指(草木花叶)脱落、衰落、零落；指老年人去世。出自唐韩愈《寄崔二十六立之》诗：“朋交日凋谢，存者逐利移。”","label":2,"words":"凋谢"},{"choose":["顶","钉","酊","叮"],"answer":"顶","pinyin":"dǐng lǐ mó bài","id":3,"discrimination":"dǐng：（顶）礼膜拜\n酩（酊）\ndīng：（钉）子\n（叮）当","title":"()礼膜拜","source":"2015北海、2015桂林","explanation":"形容对人特别恭敬（多用于贬义）。","label":2,"words":"顶礼膜拜"},{"choose":["意","义","异","议"],"answer":"义","pinyin":"duàn zhāng qǔ yì","id":4,"discrimination":"yì：断章取（义）\n创（意）\n诧（异）\n商（议）","title":"断章取()","source":"2016南宁","explanation":"指不顾全篇文章或谈话的内容，孤立地取其中的一段或一句的意思，指引用与原意不符。","label":1,"words":"断章取义"},{"choose":["惰","堕","舵","掇"],"answer":"堕","pinyin":"duò luò","id":5,"discrimination":"duò：（堕）落\n懒（惰）\n（舵）手\nzhuì：下（坠）\nduō：（掇）弄","title":"()落","source":"2016河池","explanation":"指脱落；掉落；思想行为趋于下流。","label":3,"words":"堕落"},{"choose":["蟠","翻","幡","藩"],"answer":"藩","pinyin":"fān lí","id":6,"discrimination":"fān：（藩）篱\n（翻）山越岭\n白（幡）\npán：龙（蟠）虎踞","title":"()篱","source":"2015百色","explanation":"本义是指用竹木编成的篱笆或栅栏。也比喻界域、境界，或用来指某一范畴。","label":2,"words":"藩篱"},{"choose":["复","附","缚","覆"],"answer":"覆","pinyin":"fān lái fù qù","id":7,"discrimination":"fù：翻来（覆）去\n（复）兴\n（附）和\n束（缚）","title":"翻来()去","source":"2014南宁","explanation":"原指来回翻身，现用来形容一次又一次，多次重复。出自《朱子全书》“横说也如此，竖说也如此，翻来覆去说都如此。”","label":1,"words":"翻来覆去"},{"choose":["菲","绯","蜚","啡"],"answer":"绯","pinyin":"fēi hóng","id":8,"discrimination":"fēi：（绯）红\n芳（菲）\n流言（蜚）语\n咖（啡）","title":"()红","source":"2016贺州","explanation":"绯红，中国传统色彩名称，红色的一种，艳丽的深红、鲜红、通红、深红色 。","label":4,"words":"绯红"},{"choose":["岐","祈","歧","崎"],"answer":"歧","pinyin":"fēn qí","id":9,"discrimination":"qí：分（歧）\n（岐）山\n（祈）求\n（崎）岖","title":"分()","source":"2014崇左","explanation":"两人或多人的意愿不一致，产生的对峙。","label":1,"words":"分歧"},{"choose":["偾","喷","鲼","愤"],"answer":"愤","pinyin":"fèn kǎi","id":10,"discrimination":"fèn：（愤）慨\n（偾）裂\n蝠（鲼）\npēn：（喷）泉","title":"()慨","source":"2016桂林","explanation":"指愤恨感慨、气愤不平。","label":2,"words":"愤慨"},{"choose":["糜","蘼","靡","麋"],"answer":"靡","pinyin":"fēng mǐ","id":11,"discrimination":"mǐ：风（靡）\nmí：（糜）烂\n（麋）鹿\n荼（蘼）","title":"风()","source":"2017柳州","explanation":"形容事物很风行，像风吹倒草木一样。","label":2,"words":"风靡"},{"choose":["连","怜","联","帘"],"answer":"联","pinyin":"fú xiǎng lián piān","id":12,"discrimination":"lián：浮想（联）翩\n（连）队\n（怜）爱\n窗（帘）","title":"浮想()翩","source":"2015北海","explanation":"浮想：飘浮不定的想象；联翩：鸟飞的样子，比喻连续不断。指许许多多的想象不断涌现出来。","label":1,"words":"浮想联翩"},{"choose":["谐","皆","楷","偕"],"answer":"皆","pinyin":"fù rú jiē zhī","id":13,"discrimination":"jiē：妇孺（皆）知\nxié：和（谐）\n白头（偕）老\nkǎi：（楷）书","title":"妇孺()知","source":"2014崇左","explanation":"妇女和小孩都知道，指某件事物众所周知，流传得很广。","label":2,"words":"妇孺皆知"},{"choose":["赴","负","赋","腹"],"answer":"赋","pinyin":"fù xián","id":14,"discrimination":"fù：（赋）闲\n奔（赴）\n（负）担\n（腹）地","title":"()闲","source":"2015崇左","explanation":"指没有职业在家闲着；失业在家。","label":1,"words":"赋闲"},{"choose":["煌","隍","惶","皇"],"answer":"皇","pinyin":"fù lì táng huáng","id":15,"discrimination":"huáng：富丽堂（皇）\n辉（煌）\n城（隍）庙\n惊（惶）","title":"富丽堂()","source":"2016北海","explanation":"形容房屋宏伟豪华。也形容诗文词藻华丽。","label":4,"words":"富丽堂皇"},{"choose":["罄","磬","磐","馨"],"answer":"罄","pinyin":"gào qìng","id":16,"discrimination":"qìng：告（罄）\n编（磬）\npán：（磐）石\nxīn：（馨）香","title":"告()","source":"2015崇左","explanation":"告罄是指宣告完毕。","label":2,"words":"告罄"},{"choose":["至","制","致","治"],"answer":"致","pinyin":"gé wù zhì zhī","id":17,"discrimination":"zhì：格物（致）知\n甚（至）\n（制）造\n（治）理","title":"格物()知","source":"2015来宾、2014崇左","explanation":"格：推究；致：求得。推究事物的原理法则而总结为理性知识。","label":1,"words":"格物致知"},{"choose":["模","摸","馍","膜"],"answer":"膜","pinyin":"gé mó","id":18,"discrimination":"mó：隔（膜）\n（模）型\n蒸（馍）\nmō：抚（摸）","title":"隔()","source":"2017广西北部湾经济区四市同城","explanation":"1.隔阂。2.情意不相通，彼此不了解。3.不通晓；外行。","label":2,"words":"隔膜"},{"choose":["缔","谛","蒂","帝"],"answer":"蒂","pinyin":"gēn shēn dì gù","id":19,"discrimination":"dì：根深（蒂）固\n（缔）造\n真（谛）\n（帝）王","title":"根深()固","source":"2014来宾、2014梧州","explanation":"蒂：瓜、果与茎、枝相连的部分；固：牢固。比喻基础稳固，不容易动摇。","label":4,"words":"根深蒂固"},{"choose":["畴","踌","筹","酬"],"answer":"筹","pinyin":"gèng shèng yī chóu","id":20,"discrimination":"chóu：更胜一（筹）\n范（畴）\n（踌）躇\n\n","title":"更胜一()","source":"2014南宁","explanation":"筹：计数的用具；谋划。胜：指超过。指技艺或技能超过别人。","label":4,"words":"更胜一筹"},{"choose":["钩","沟","购","勾"],"answer":"勾","pinyin":"gōu lè","id":1,"discrimination":"gōu：（勾）勒\n鱼（钩）\n（沟）壑\ngòu：（购）买","title":"()勒","source":"2016河池","explanation":"指用线条画出轮廓；双钩。勾勒是中国技法的名称之一。","label":2,"words":"勾勒"},{"choose":["缕","偻","褛","楼"],"answer":"偻","pinyin":"gōu  lóu","id":2,"discrimination":"lóu：佝（偻）\n（楼）房\nlǚ：千丝万（缕）\n褴（褛）","title":"佝()","source":"2014百色","explanation":"脊背向前弯曲。","label":2,"words":"佝偻"},{"choose":["劈","譬","僻","辟"],"answer":"僻","pinyin":"gū pì","id":3,"discrimination":"pì：孤（僻）\n（譬）如\n开（辟）\npī：（劈）风斩浪","title":"孤()","source":"2016贺州","explanation":"性情孤独怪异，难与常人相处。","label":3,"words":"孤僻"},{"choose":["明","铭","名","冥"],"answer":"名","pinyin":"gù míng sī yì","id":4,"discrimination":"míng：顾（名）思义\n（明）天\n（铭）记\n（冥）思苦想","title":"顾()思义","source":"2016梧州、2014来宾","explanation":"顾：看；义：意义，含义。从名称想到其所包含的意义。语出《三国志·魏书·王昶传》：“欲使汝曹顾名思义，不敢违越也。”","label":1,"words":"顾名思义"},{"choose":["舔","恬","聒","舐"],"answer":"聒","pinyin":"guō zào","id":5,"discrimination":"guō：（聒）噪\ntiǎn：（舔）唇咂嘴\ntián：（恬）静\nshì：（舐）犊情深","title":"()噪","source":"2015崇左","explanation":"声音杂乱；吵闹。","label":2,"words":"聒噪"},{"choose":["誓","逝","浙","势"],"answer":"誓","pinyin":"hǎi shì shān méng","id":6,"discrimination":"shì：海（誓）山盟\n（逝）世\n（势）力\nzhè：（浙）江","title":"海()山盟","source":"2017梧州","explanation":"多指恋人间对未来生活的盟约和誓言，表达自己对爱人的信任以及对美好爱情和生活的向往和追求。","label":3,"words":"海誓山盟"},{"choose":["涵","寒","含","函"],"answer":"含","pinyin":"hán xīn rú kǔ","id":7,"discrimination":"hán：（含）辛茹苦\n（涵）养\n（寒）冷\n（函）数","title":"()辛茹苦","source":"2014贺州","explanation":"辛：辣；茹：吃。形容受尽辛苦和吃尽苦头。","label":1,"words":"含辛茹苦"},{"choose":["翰","悍","憾","瀚"],"answer":"瀚","pinyin":"hào hàn","id":8,"discrimination":"hàn：浩（瀚）\n（翰）林\n强（悍）\n遗（憾）","title":"浩()","source":"2014南宁、2016河池","explanation":"1.水势广大的样子。2.广阔的。3.大量的。","label":1,"words":"浩瀚"},{"choose":["煦","洵","询","旭"],"answer":"煦","pinyin":"hé xù","id":9,"discrimination":"xù：和（煦）\n（旭）日东升\nxún：（洵）直\n（询）问","title":"和()","source":"2015百色、2014百色","explanation":"形容温暖的阳光。","label":3,"words":"和煦"},{"choose":["哄","烘","供","洪"],"answer":"烘","pinyin":"hōng tuō","id":10,"discrimination":"hōng：（烘）烤\n（哄）堂大笑\nhóng：（洪）亮\ngōng：提（供）","title":"()托","source":"2017广西北部湾经济区四市同城","explanation":"指陪衬，使明显突出；中国画技法名；文学创作的一种表现手法，即通过侧面描写，使所要表现的事物鲜明突出。","label":2,"words":"烘托"},{"choose":["妆","装","庄","桩"],"answer":"装","pinyin":"hóng zhuāng sù guǒ","id":11,"discrimination":"zhuāng：红（装）素裹\n梳（妆）台\n（庄）重\n木（桩）","title":"红()素裹","source":"2015来宾","explanation":"形容雪后初晴，红日与白雪交相辉映的景象。","label":1,"words":"红装素裹"},{"choose":["半","拌","伴","绊"],"answer":"伴","pinyin":"hū péng yǐn bàn","id":12,"discrimination":"bàn：呼朋引（伴）\n（半）天\n搅（拌）\n（绊）倒","title":"呼朋引()","source":"2014河池","explanation":"呼唤朋友，招引同伴。引：牵引，招引。常用于鸟类招呼同伴。","label":4,"words":"呼朋引伴"},{"choose":["斩","展","崭","辗"],"answer":"展","pinyin":"huā zhī zhāo zhǎn","id":13,"discrimination":"zhǎn：花枝招（展）\n（斩）断\n（崭）新\n（辗）转","title":"花枝招()","source":"2015来宾","explanation":"比喻姿态优美。招展，迎风摆动。","label":1,"words":"花枝招展"},{"choose":["猾","滑","划","华"],"answer":"滑","pinyin":"huá jī","id":14,"discrimination":"huá：（滑）稽\n狡（猾）\n（划）船\n（华）丽","title":"()稽","source":"2017河池","explanation":"1.（言语、动作或姿态）引人发笑。2.〈名〉曲艺的一种，流行于上海和江浙一带，近似于北方的相声。","label":1,"words":"滑稽"},{"choose":["焕","唤","换","涣"],"answer":"唤","pinyin":"huàn xǐng","id":15,"discrimination":"huàn：（唤）醒\n（焕）然一新\n交（换）\n（涣）散","title":"()醒","source":"2016柳州","explanation":"叫醒；常用作比喻，有使之觉醒的意思。","label":4,"words":"唤醒"},{"choose":["洛","禄","恪","赂"],"answer":"赂","pinyin":"huì lù","id":16,"discrimination":"lù：贿（赂）\n无功受（禄）\nluò：（洛）阳\nkè：（恪）守","title":"贿()","source":"2014贺州","explanation":"1.用财物买通别人。2.用来买通别人的财物。","label":3,"words":"贿赂"},{"choose":["汇","诲","贿","讳"],"answer":"讳","pinyin":"jì huì","id":17,"discrimination":"huì：忌（讳）\n（汇）集\n教（诲）\n（贿）赂","title":"忌()","source":"2017贺州","explanation":"因风俗习惯或畏惧权势而对某些不吉利的语言或举动有所顾忌，对某些问题可能产生不利后果的事力求避免。","label":1,"words":"忌讳"},{"choose":["域","驭","喻","御"],"answer":"驭","pinyin":"jià yù","id":18,"discrimination":"yù：驾（驭）\n领（域）\n比（喻）\n抵（御）","title":"驾()","source":"2016钦州","explanation":"1.驱使车马。 2.比喻掌握控制；支配。","label":1,"words":"驾驭"},{"choose":["骄","矫","轿","娇"],"answer":"骄","pinyin":"jiāo shē","id":19,"discrimination":"jiāo：（骄）奢\n（娇）艳\njiǎo：（矫）健\njiào：（轿）车","title":"()奢","source":"2016梧州","explanation":"1.骄纵的品性行为。2.骄横奢侈。","label":2,"words":"骄奢"},{"choose":["绞","姣","胶","狡"],"answer":"狡","pinyin":"jiǎo huá","id":20,"discrimination":"jiǎo：（狡）猾\n（绞）刑\njiāo：（姣）好\n（胶）囊","title":"()猾","source":"2014贺州","explanation":"指诡诈不可信，狡诈刁钻。","label":2,"words":"狡猾"},{"choose":["蹂","揉","柔","糅"],"answer":"揉","pinyin":"jiǎo róu zào zuò","id":1,"discrimination":"róu：矫（揉）造作\n（蹂）躏\n（柔）软\n（糅）合","title":"矫()造作","source":"2017贺州","explanation":"形容过分做作，极不自然。矫：使弯的变成直的；揉：使直的变成弯的。","label":4,"words":"矫揉造作"},{"choose":["绞","狡","皎","饺"],"answer":"皎","pinyin":"jiǎo jié","id":2,"discrimination":"jiǎo：（皎）洁\n（绞）尽脑汁\n（狡）猾\n水（饺）","title":"()洁","source":"2017河池、2014河池","explanation":"(月光)明亮洁白。","label":4,"words":"皎洁"},{"choose":["拮","诘","结","洁"],"answer":"诘","pinyin":"jié zé","id":3,"discrimination":"jié：（诘）责\n（拮）据\n（结）账\n（洁）白","title":"()责","source":"2015崇左","explanation":"质问并责备。","label":4,"words":"诘责"},{"choose":["桔","秸","诘","拮"],"answer":"拮","pinyin":"jié jū","id":4,"discrimination":"jié：（拮）据\n（桔）梗\n（诘）责\njiē：（秸）秆","title":"()据","source":"2017贺州、2014崇左、2016梧州","explanation":"指生活贫困，缺少钱，情况窘迫。","label":2,"words":"拮据"},{"choose":["接","结","孑","截"],"answer":"截","pinyin":"jié rán bù tóng","id":5,"discrimination":"jié：（截）然不同\n（结）束\n（孑）然一身\njiē：直（接）","title":"()然不同","source":"2014玉林、防城港","explanation":"事物之间，界限分明，全然不一样。","label":3,"words":"截然不同"},{"choose":["皇","隍","煌","惶"],"answer":"煌","pinyin":"jīn bì huī huáng","id":6,"discrimination":"huáng：金碧辉（煌）\n（皇）帝\n城（隍）庙\n惊（惶）","title":"金碧辉()","source":"2017河池","explanation":"形容建筑物异常华丽，光彩夺目。","label":4,"words":"金碧辉煌"},{"choose":["妗","吟","矜","衿"],"answer":"矜","pinyin":"jīn chí","id":7,"discrimination":"jīn：（矜）持\n青（衿）\njìn：（妗）子\nyín：（吟）唱","title":"()持","source":"2015玉林、防城港","explanation":"1.庄重；严肃 。2.拘谨；拘束。","label":2,"words":"矜持"},{"choose":["维","唯","惟","潍"],"answer":"维","pinyin":"jìn tuì wéi gǔ","id":8,"discrimination":"wéi：进退（维）谷\n（唯）恐\n（惟）妙（惟）肖\n（潍）坊","title":"进退()谷","source":"2015来宾、2014梧州","explanation":"无论是进还是退，都是处在困境之中。形容处境艰难，进退两难。语出《诗经·大雅·桑柔》：“人亦有言：进退维谷。”","label":4,"words":"进退维谷"},{"choose":["荒","谎","慌","蔬"],"answer":"慌","pinyin":"jīng huāng shī cuò","id":9,"discrimination":"huāng：惊（慌）失措\n饥（荒）\nhuǎng：撒（谎）\nshū：（蔬）菜","title":"惊()失措","source":"2014梧州","explanation":"指吓得慌了手脚，不知如何是好。","label":2,"words":"惊慌失措"},{"choose":["睛","靖","静","精"],"answer":"精","pinyin":"jīng yì qiú jīng","id":10,"discrimination":"jīng：（精）益求精\n眼（睛）\njìng：绥（靖）\n安（静）","title":"()益求精","source":"2015玉林、防城港","explanation":"比喻已经很好了，还要求更好。","label":2,"words":"精益求精"},{"choose":["炯","恫","洞","迥"],"answer":"迥","pinyin":"jiǒng hū bù tóng","id":11,"discrimination":"jiǒng：（迥）乎不同\n（炯）（炯）有神\ndòng：（恫）吓\n地（洞）","title":"()乎不同","source":"2014崇左","explanation":"迥：差得远。形容差别很大，完全不一样。","label":2,"words":"迥乎不同"},{"choose":["誊","誉","眷","春"],"answer":"眷","pinyin":"juàn gù","id":12,"discrimination":"juàn：（眷）顾\nténg：（誊）写\nyù：名（誉）\nchūn：初（春）","title":"()顾","source":"2016河池、2016桂林","explanation":"指眷念，思念。","label":2,"words":"眷顾"},{"choose":["窍","巧","朽","俏"],"answer":"窍","pinyin":"jué qiào","id":13,"discrimination":"qiào：诀（窍）\n（俏）丽\nqiǎo：花言（巧）语\nxiǔ：腐（朽）","title":"诀()","source":"2015玉林、防城港","explanation":"关键性的好办法。","label":3,"words":"诀窍"},{"choose":["俊","竣","骏","峻"],"answer":"竣","pinyin":"jùn gōng","id":14,"discrimination":"jùn：（竣）工\n英（俊）\n（骏）马\n险（峻）","title":"()工","source":"2014贺州","explanation":"工程完工验收合格。","label":4,"words":"竣工"},{"choose":["藻","燥","澡","躁"],"answer":"燥","pinyin":"kū zào","id":15,"discrimination":"zào：枯（燥）\n烦（躁）\nzǎo：海（藻）\n洗（澡）","title":"枯()","source":"2016贺州","explanation":"单调，没有趣味。语出汉蔡邕《蝉赋》：“声嘶嗌以沮败，体枯燥以冰凝。”","label":2,"words":"枯燥"},{"choose":["指","旨","诣","谐"],"answer":"诣","pinyin":"kǔ xīn gū yì","id":16,"discrimination":"yì：苦心孤（诣）\nzhǐ：手（指）\n主（旨）\nxié：和（谐）","title":"苦心孤()","source":"2015梧州","explanation":"费尽心思钻研或经营，达到别人达不到的境地。孤诣：独自达到的境地。","label":2,"words":"苦心孤诣"},{"choose":["炙","灸","治","炽"],"answer":"炙","pinyin":"kuài zhì rén kǒu","id":17,"discrimination":"zhì：脍（炙）人口\n（治）理\njiǔ：针（灸）\nchì：（炽）热","title":"脍()人口","source":"2015玉林、防城港、2014北海","explanation":"脍和炙都是美味的食品。比喻好的诗文为人们赞美和传诵。","label":3,"words":"脍炙人口"},{"choose":["倘","淌","敝","敞"],"answer":"敞","pinyin":"kuān chang","id":18,"discrimination":"chǎng：（敞）亮\ntǎng：（倘）若\n流（淌）\nbì：凋（敝）","title":"宽()","source":"2017广西北部湾经济区四市同城","explanation":"指宽大、开阔、宽阔。语出《东观汉记·刘般传》：“时五校官显职闲，而府寺宽敞，舆服光丽。”。","label":2,"words":"宽敞"},{"choose":["怒","驽","述","恕"],"answer":"恕","pinyin":"kuān shù","id":19,"discrimination":"shù：宽（恕）\n描（述）\nnù：发（怒）\nnú：（驽）钝","title":"宽()","source":"2016崇左、2016北海","explanation":"宽容饶恕。","label":3,"words":"宽恕"},{"choose":["框","匡","哐","诓"],"answer":"诓","pinyin":"kuāng piàn","id":20,"discrimination":"kuāng：（诓）骗\n（匡）扶\n（哐）啷\nkuàng：门（框）","title":"()骗","source":"2016梧州、2015崇左","explanation":"说谎话骗人。","label":2,"words":"诓骗"},{"choose":["枉","忘","妄","佞"],"answer":"妄","pinyin":"kuáng wàng zì dà","id":1,"discrimination":"wàng：狂（妄）自大\n（忘）恩负义\nwǎng：（枉）费\nnìng：（佞）臣","title":"狂()自大","source":"2014梧州","explanation":"指极其放肆，自高自大，目中无人。语出《旧唐书·皇甫雞传》：“执谊；叔文乘时多僻；而欲斡运六合；斟酌万几；……何狂妄之甚也。”。","label":3,"words":"狂妄自大"},{"choose":["窥","规","馈","溃"],"answer":"馈","pinyin":"kuì zèng","id":2,"discrimination":"kuì：（馈）赠\n（溃）散\nkuī：偷（窥）\nguī：（规）定","title":"()赠","source":"2017梧州、2015来宾","explanation":"本义是以食物送人，把财物无代价地送给别人，也指赠送的东西、礼品。","label":3,"words":"馈赠"},{"choose":["淖","棹","悼","绰"],"answer":"绰","pinyin":"kuò chuò","id":3,"discrimination":"chuò：阔（绰）\nnào：泥（淖）\nzhào：（棹）船\ndào：哀（悼）","title":"阔()","source":"2015来宾","explanation":"生活奢侈，讲究排场。","label":2,"words":"阔绰"},{"choose":["腊","错","蜡","惜"],"answer":"蜡","pinyin":"là zhú","id":4,"discrimination":"là：（蜡）烛\n（腊）月\ncuò：（错）落\nxī：吝（惜）","title":"()烛","source":"2015钦州","explanation":"一种日常照明工具，主要用石蜡制成，在古代，通常由动物油脂制造。可燃烧发出光亮。","label":2,"words":"蜡烛"},{"choose":["揽","篮","滥","褴"],"answer":"褴","pinyin":"lán lǚ","id":5,"discrimination":"lán：（褴）褛\n（篮）球\nlǎn：招（揽）\nlàn：陈词（滥）调","title":"()褛","source":"2015贺州","explanation":"指衣服破烂，不整洁，十分凌乱，不堪入目。","label":3,"words":"褴褛"},{"choose":["曼","漫","蔓","慢"],"answer":"漫","pinyin":"làn màn","id":6,"discrimination":"màn：烂（漫）\n（曼）妙\n（蔓）延\n（慢）热","title":"烂()","source":"2017梧州","explanation":"1.也作烂熳、烂缦。2.形容颜色鲜丽。3.形容坦率自然，毫不做作。","label":4,"words":"烂漫"},{"choose":["籍","汲","辑","藉"],"answer":"藉","pinyin":"láng jí","id":7,"discrimination":"jí：狼（藉）\n书（籍）\n（汲）取\n编（辑）","title":"狼()","source":"2017河池、2014来宾、2015河池、2015崇左、2016南宁","explanation":"乱七八糟；杂乱不堪。","label":1,"words":"狼藉"},{"choose":["赢","擂","儡","羸"],"answer":"羸","pinyin":"léi ruò","id":8,"discrimination":"léi：（羸）弱\n自吹自（擂）\nyíng：（赢）家\nlěi：傀（儡）","title":"()弱","source":"2015崇左","explanation":"瘦弱。","label":3,"words":"羸弱"},{"choose":["黎","黧","离","厘"],"answer":"黎","pinyin":"lí mín bǎi xìng","id":9,"discrimination":"lí：（黎）民百姓\n（黧）黑\n分（离）\n（厘）米","title":"()民百姓","source":"2014南宁","explanation":"指普通老百姓。","label":1,"words":"黎民百姓"},{"choose":["撩","嘹","缭","瞭"],"answer":"嘹","pinyin":"liáo liàng","id":10,"discrimination":"liáo：（嘹）亮\n（撩）拨\n（缭）绕\nliào：（瞭）望","title":"()亮","source":"2017梧州、2014北海、2014钦州、2015柳州、2016南宁、2017河池","explanation":"声音清晰圆润而响亮。","label":2,"words":"嘹亮"},{"choose":["鳞","麟","嶙","磷"],"answer":"嶙","pinyin":"lín xún","id":11,"discrimination":"lín：（嶙）峋\n鱼（鳞）\n麒（麟）\n（磷）火","title":"()峋","source":"2017广西北部湾经济区四市同城、2014来宾、2014钦州、2015崇左、2016桂林、2016贺州","explanation":"1.形容山石等突兀、重叠。2.形容人消瘦露骨。3.形容人刚正有骨气。","label":4,"words":"嶙峋"},{"choose":["粼","鳞","磷","嶙"],"answer":"鳞","pinyin":"lín cì zhì bǐ","id":12,"discrimination":"lín：（鳞）次栉比\n波光（粼）（粼）\n（磷）火\n（嶙）峋","title":"()次栉比","source":"2015梧州","explanation":"像鱼鳞和梳子的齿一样，一个挨着一个地排列着，多用来形容房屋等密集。","label":4,"words":"鳞次栉比"},{"choose":["冽","咧","列","例"],"answer":"冽","pinyin":"lǐn liè","id":13,"discrimination":"liè：凛（冽）\n罗（列）\nliě：（咧）嘴\nlì：条（例）","title":"凛()","source":"2017柳州","explanation":"极为寒冷，严寒刺骨。常用于形容隆冬时的寒风。","label":2,"words":"凛冽"},{"choose":["珑","茏","笼","龙"],"answer":"珑","pinyin":"líng lóng","id":14,"discrimination":"lóng：玲（珑）\n葱（茏）\n蒸（笼）\n（龙）骨","title":"玲()","source":"2014河池","explanation":"原意为娇小灵活之意,指物体精巧细致。也指人灵巧敏捷。","label":4,"words":"玲珑"},{"choose":["缆","榄","揽","览"],"answer":"览","pinyin":"liú lǎn","id":15,"discrimination":"lǎn：浏（览）\n光（缆）\n橄（榄）\n包（揽）","title":"浏()","source":"2015贺州","explanation":"大略地看。","label":4,"words":"浏览"},{"choose":["镂","搂","楼","蝼"],"answer":"镂","pinyin":"lòu kōng","id":16,"discrimination":"lòu：（镂）空\nlǒu：（搂）抱\nlóu：（楼）阁\n（蝼）蚁","title":"()空","source":"2015来宾","explanation":"在物体上雕刻出穿透物体的花纹或文字。","label":2,"words":"镂空"},{"choose":["谩","漫","慢","曼"],"answer":"漫","pinyin":"màn bù jīng xīn","id":17,"discrimination":"màn：（漫）不经心\n（谩）骂\n（慢）吞吞\n（曼）妙","title":"()不经心","source":"2015贺州","explanation":"随随便便，不放在心上。也说漫不经意。","label":4,"words":"漫不经心"},{"choose":["魅","袂","媚","寐"],"answer":"魅","pinyin":"mèi lì","id":18,"discrimination":"mèi：（魅）力\n联（袂）\n明（媚）\n假（寐）","title":"()力","source":"2014贺州","explanation":"形容一个人的个性与容貌之美有着很强的诱惑力与吸引力。","label":1,"words":"魅力"},{"choose":["槛","滥","褴","尴"],"answer":"槛","pinyin":"mén kǎn","id":19,"discrimination":"kǎn：门（槛）\nlàn：泛（滥）\nlán：（褴）褛\ngān：（尴）尬","title":"门()","source":"2014钦州","explanation":"1.门框下端的横木条、石条或金属条。2.诀窍，也指精打细算或占便宜的本领。3.比喻进入某范围的标准或条件。","label":2,"words":"门槛"},{"choose":["迷","靡","谜","弥"],"answer":"弥","pinyin":"mí màn","id":20,"discrimination":"mí：（弥）漫\n（迷）路\n奢（靡）\n（谜）语","title":"()漫","source":"2017贺州","explanation":"（烟尘、雾气、水等）充满；布满。","label":1,"words":"弥漫"},{"choose":["觑","墟","虚","趣"],"answer":"觑","pinyin":"miàn miàn xiāng qù","id":1,"discrimination":"qù：面面相（觑）\n（趣）味\nxū：废（墟）\n（虚）弱","title":"面面相()","source":"2015崇左","explanation":"你看我，我看你，不知道如何是好。形容人们因惊惧或无可奈何而互相看着，都不说话。","label":3,"words":"面面相觑"},{"choose":["纱","抄","秒","妙"],"answer":"妙","pinyin":"miào shǒu ǒu dé","id":2,"discrimination":"miào：（妙）手偶得\nshā：（纱）窗\nchāo：（抄）送\nmiǎo：（秒）杀","title":"()手偶得","source":"2014玉林、防城港","explanation":"指技术高超的人，偶然间得到的灵感或作品。也用来形容文学素养很深的人，出于灵感，即可偶然间得到妙语佳作。","label":2,"words":"妙手偶得"},{"choose":["幅","副","福","辐"],"answer":"副","pinyin":"míng fù qí shí","id":3,"discrimination":"fù：名（副）其实\nfú：（幅）员辽阔\n（福）气\n（辐）射","title":"名()其实","source":"2017河池、2014玉林、防城港、2014北海、2015河池","explanation":"名声或称谓（号）与实际一致、相符合。","label":2,"words":"名副其实"},{"choose":["冥","铭","明","名"],"answer":"冥","pinyin":"míng sī xiá xiǎng","id":4,"discrimination":"míng：（冥）思遐想\n（铭）记\n（明）显\n（名）讳","title":"()思遐想","source":"2014百色","explanation":"遇到问题后长时间、多角度地从远处思索。","label":1,"words":"冥思遐想"},{"choose":["冥","名","瞑","茗"],"answer":"瞑","pinyin":"míng mù","id":5,"discrimination":"míng：（瞑）目\n（冥）思苦想\n（名）字\n品（茗）","title":"()目","source":"2015河池","explanation":"指闭上眼睛,多指人死时无所牵挂。","label":1,"words":"瞑目"},{"choose":["漠","陌","莫","默"],"answer":"莫","pinyin":"mò zhōng yī shì","id":6,"discrimination":"mò：（莫）衷一是\n（漠）然\n（陌）生\n（默）契","title":"()衷一是","source":"2015梧州","explanation":"各有各的意见、说法，不能得出一致的结论。语出清·吴趼人《痛史》：“议论纷纷；莫衷一是。”","label":1,"words":"莫衷一是"},{"choose":["莫","漠","模","膜"],"answer":"漠","pinyin":"mò bù guān xīn","id":7,"discrimination":"mò：（漠）不关心\n（莫）衷一是\nmó：（模）仿\n角（膜）","title":"()不关心","source":"2016钦州","explanation":"形容对人或事物冷淡，一点也不关心。","label":2,"words":"漠不关心"},{"choose":["媒","苜","眸","牟"],"answer":"牟","pinyin":"móu qǔ","id":8,"discrimination":"móu：（牟）取\n明（眸）\nmù：（苜）蓿\nméi：（媒）体","title":"()取","source":"2016梧州","explanation":"谋取（名利）。","label":3,"words":"牟取"},{"choose":["囊","囔","攮","齉"],"answer":"囊","pinyin":"náng yíng yìng xuě","id":9,"discrimination":"náng：（囊）萤映雪\nnāng：（囔）（囔）\nnǎng：（攮）子\nnàng：（齉）鼻儿","title":"()萤映雪","source":"2015百色","explanation":"原是车胤用口袋装萤火虫来照书本，孙康利用雪的反光勤奋苦学的故事。后形容刻苦攻读。语出元·贾仲名《萧淑兰》第一折：“虽无汗马眠霜苦，曾受囊萤映雪劳。”","label":4,"words":"囊萤映雪"},{"choose":["脑","恼","挠","瑙"],"answer":"恼","pinyin":"nǎo xiū chéng nù","id":10,"discrimination":"nǎo：（恼）羞成怒\n（脑）袋\n玛（瑙）\nnáo：（挠）头","title":"()羞成怒","source":"2016梧州","explanation":"因气恼和羞愧而恼怒。指因自己一些难于启齿的事情被人戳穿而羞恼，发怒。","label":3,"words":"恼羞成怒"},{"choose":["髓","隧","隋","随"],"answer":"髓","pinyin":"nǎo suǐ","id":11,"discrimination":"suǐ：脑（髓）\nsuì：（隧）道\nsuí：（隋）代\n（随）意","title":"脑()","source":"2015百色","explanation":"指脑浆。","label":2,"words":"脑髓"},{"choose":["凝","疑","颖","颍"],"answer":"凝","pinyin":"níng gù","id":12,"discrimination":"níng：（凝）固\nyí：（疑）惑\nyǐng：新（颖）\n（颍）河","title":"()固","source":"2017桂林","explanation":"指在温度降低时，物质由液态变为固态的过程，物质凝固时的温度称为凝固点。","label":2,"words":"凝固"},{"choose":["纽","忸","扭","钮"],"answer":"纽","pinyin":"niǔ dài","id":13,"discrimination":"niǔ：（纽）带\n（忸）怩\n（扭）捏作态\n电（钮）","title":"()带","source":"2017河池","explanation":"指起到联系作用的东西，它是具有一个“线状”的意义。比喻起联系作用的人或事物。","label":4,"words":"纽带"},{"choose":["茁","绌","础","拙"],"answer":"拙","pinyin":"nòng qiǎo chéng zhuō","id":14,"discrimination":"zhuō：弄巧成（拙）\nzhuó：（茁）壮\nchù：相形见（绌）\nchǔ：基（础）","title":"弄巧成()","source":"2014桂林","explanation":"本想卖弄聪明，结果做了蠢事。语出宋黄庭坚《拙轩颂》：“弄巧成拙，画蛇添足。”","label":2,"words":"弄巧成拙"},{"choose":["谒","揭","堨","遏"],"answer":"遏","pinyin":"nù bù kě è","id":15,"discrimination":"è：怒不可（遏）\nyè：（谒）见\njiē：（揭）开\nài：石（堨）","title":"怒不可()","source":"2014贵港","explanation":"愤怒得不能抑制，形容愤怒到了极点。语出《资治通鉴·后唐明宗天成二年》：“严惶怖求哀，知祥曰：‘众怒不可遏也！’遂辑下，斩之。”","label":2,"words":"怒不可遏"},{"choose":["怄","殴","呕","沤"],"answer":"呕","pinyin":"ǒu xīn lì xuè","id":16,"discrimination":"ǒu：（呕）心沥血\nòu：（怄）气\n（沤）肥\nōu：（殴）打","title":"()心沥血","source":"2015贺州","explanation":"比喻费尽心血。多用来形容工作、事业、文艺创作等方面用心的艰苦。 语出唐·韩愈《归彭城》诗：“刳肝以为纸；沥血以书辞。”","label":2,"words":"呕心沥血"},{"choose":["樊","焚","蹒","攀"],"answer":"攀","pinyin":"pān fù","id":17,"discrimination":"pān：（攀）附\nfán：（樊）笼\nfén：（焚）烧\npán：（蹒）跚","title":"()附","source":"2014桂林","explanation":"指附着东西往上爬；比喻投靠有权势的人，以求高升。","label":3,"words":"攀附"},{"choose":["蝉","婵","禅","缠"],"answer":"缠","pinyin":"pán chan","id":18,"discrimination":"chán：（缠）绕\n（蝉）鸣\n（婵）娟\n坐（禅）","title":"盘()","source":"2016梧州","explanation":"旅费、路费。","label":1,"words":"盘缠"},{"choose":["踌","懑","磐","蹒"],"answer":"蹒","pinyin":"pán shān","id":19,"discrimination":"pán：（蹒）跚\n（磐）石\nchóu：（踌）躇\nmèn：愤（懑）","title":"()跚","source":"2016崇左、2016桂林","explanation":"腿脚不灵便，走路缓慢、摇摆的样子。","label":3,"words":"蹒跚"},{"choose":["篷","缝","蓬","逢"],"answer":"蓬","pinyin":"péng bó","id":20,"discrimination":"péng：（蓬）勃\n（篷）车\nféng：相（逢）\n（缝）补","title":"()勃","source":"2016崇左、2015柳州","explanation":"形容事物繁荣茂盛。语出汉贾谊《旱云赋》：“遥望白云之蓬勃兮，滃澹澹而妄止。”","label":2,"words":"蓬勃"},{"choose":["篷","蓬","逢","缝"],"answer":"蓬","pinyin":"péng hāo","id":1,"discrimination":"péng：（蓬）蒿\n（篷）车\nféng：相（逢）\n（缝）补","title":"()蒿","source":"2015来宾","explanation":"1.茼蒿。2.飞蓬和蒿子。借指草野民间。","label":2,"words":"蓬蒿"},{"choose":["膨","棚","澎","鹏"],"answer":"澎","pinyin":"péng pài","id":2,"discrimination":"péng：（澎）湃\n（膨）胀\n（棚）车\n（鹏）程万里","title":"()湃","source":"2015来宾","explanation":"1.形容波浪互相撞击。2.比喻声势浩大，气势雄伟。语出唐·韩愈 《送惠师》诗：“微风吹木石，澎湃闻韶钧。”","label":1,"words":"澎湃"},{"choose":["啤","牌","脾","睥"],"answer":"睥","pinyin":"pì nì","id":3,"discrimination":"pì：（睥）睨\npí：（啤）酒\n（脾）气\npái：名（牌）","title":"()睨","source":"2015崇左","explanation":"指斜着眼看，有厌恶或高傲的意思。","label":2,"words":"睥睨"},{"choose":["剽","镖","瞟","膘"],"answer":"剽","pinyin":"piāo hàn","id":4,"discrimination":"piāo：（剽）悍\nbiāo：飞（镖）\n长（膘）\npiǎo：（瞟）闪","title":"()悍","source":"2017贺州、2017桂林","explanation":"形容敏捷而勇猛，灵活而勇敢。语出《汉书·陈汤传》：“且其人剽悍，好战伐，数取胜，久畜之，必为西域患。”","label":2,"words":"剽悍"},{"choose":["及","汲","急","极"],"answer":"及","pinyin":"pò bù jí dài","id":5,"discrimination":"jí：迫不（及）待\n（汲）取\n（急）忙\n积（极）","title":"迫不()待","source":"2016崇左","explanation":"形容心情十分急切，急迫得不能再等待。语出清·李汝珍《镜花缘》第六回：“且系酒后游戏，该仙子何以迫不及待。”","label":1,"words":"迫不及待"},{"choose":["釜","斧","腐","府"],"answer":"釜","pinyin":"pò fǔ chén zhōu","id":6,"discrimination":"fǔ：破（釜）沉舟\n（斧）头\n（腐）烂\n官（府）","title":"破()沉舟","source":"2014百色","explanation":"把饭锅打破，把渡船凿沉，比喻不留退路，非打胜仗不可，下决心不顾一切地干到底。语出《孙子兵法·九地》：“焚舟破釜，若驱群羊而往，驱而来，莫知所之。”","label":1,"words":"破釜沉舟"},{"choose":["葡","脯","浦","匍"],"answer":"匍","pinyin":"pú fú","id":7,"discrimination":"pú：（匍）匐\n（葡）萄\n胸（脯）\npǔ：（浦）口","title":"()匐","source":"2014来宾","explanation":"指爬行或爬。语出《诗·大雅·生民》：“诞实匍匐，克岐克嶷，以就口食。”","label":2,"words":"匍匐"},{"choose":["跷","饶","翘","浇"],"answer":"跷","pinyin":"qī qiāo","id":8,"discrimination":"qiāo：蹊（跷）\nráo：富（饶）\nqiáo：（翘）楚\njiāo：（浇）水","title":"蹊()","source":"2014贺州","explanation":"指奇怪、可疑。","label":2,"words":"蹊跷"},{"choose":["沂","析","祈","忻"],"answer":"祈","pinyin":"qí dǎo","id":9,"discrimination":"qí：（祈）祷\nyí：（沂）垠\nxī：分（析）\nxīn：（忻）慕","title":"()祷","source":"2014崇左","explanation":"一种宗教仪式，信仰宗教的人向神默告自己的愿望。语出《后汉书·栾巴传》：“郡土多山川鬼怪，小人常破赀产以祈祷。”","label":2,"words":"祈祷"},{"choose":["畸","绮","崎","琦"],"answer":"绮","pinyin":"qǐ lì","id":10,"discrimination":"qǐ：（绮）丽\njī：（畸）形\nqí：（崎）岖\n（琦）行","title":"()丽","source":"2015河池、2014玉林、防城港","explanation":"形容华美艳丽。语出李白《古风》之一云：“自从建安来，绮丽不足珍。”","label":2,"words":"绮丽"},{"choose":["徒","陡","徙","赴"],"answer":"徙","pinyin":"qiān xǐ","id":11,"discrimination":"xǐ：迁（徙）\ntú：（徒）弟\ndǒu：（陡）峭\nfù：奔（赴）","title":"迁()","source":"2015北海","explanation":"1.迁移，改变居住的地方。2.动物学上指鸟类依季节不同而变更栖居地区。","label":2,"words":"迁徙"},{"choose":["涌","佣","拥","蛹"],"answer":"拥","pinyin":"qián hū hòu yōng","id":12,"discrimination":"yōng：前呼后（拥）\n（佣）人\nyǒng：（涌）现\n蚕（蛹）","title":"前呼后()","source":"2014桂林","explanation":"前面有人吆喝开路，后面有人簇拥护卫。多形容旧时官吏出巡时的声势。","label":2,"words":"前呼后拥"},{"choose":["虏","虐","虎","虔"],"answer":"虔","pinyin":"qián chéng","id":13,"discrimination":"qián：（虔）诚\nlǔ：俘（虏）\nnüè：暴（虐）\nhǔ：老（虎）","title":"()诚","source":"2016河池","explanation":"指恭敬而有诚意的态度。语出北周·庾信 《祀五帝歌》：“朱弦绛鼓罄虔诚，万物含养各长生。”","label":2,"words":"虔诚"},{"choose":["轮","纶","伦","抡"],"answer":"伦","pinyin":"qiǎo miào jué lún","id":14,"discrimination":"lún：巧妙绝（伦）\n车（轮）\n垂（纶）\n（抡）锤","title":"巧妙绝()","source":"2014梧州","explanation":"方法或技术灵巧高明，超乎寻常，无与伦比。","label":4,"words":"巧妙绝伦"},{"choose":["楔","锲","挈","契"],"answer":"锲","pinyin":"qiè ér bù shě","id":15,"discrimination":"qiè：（锲）而不舍\n提纲（挈）领\nxiē：（楔）子\nqì：（契）丹","title":"()而不舍","source":"2015百色","explanation":"不断地雕刻，比喻有恒心，有毅力。 语出《荀子·劝学》：“锲而舍之，朽木不折；锲而不舍，金石可镂。”","label":2,"words":"锲而不舍"},{"choose":["劫","截","洁","捷"],"answer":"捷","pinyin":"qīng jié","id":16,"discrimination":"jié：轻（捷）\n浩（劫）\n（截）止\n（洁）白","title":"轻()","source":"2016崇左","explanation":"指动作轻快敏捷。语出《三国志·吴志·贺齐传》：“ 齐身出周行，观视形便，阴募轻捷士，为作铁弋。”","label":1,"words":"轻捷"},{"choose":["沈","忱","枕","眈"],"answer":"忱","pinyin":"rè chén","id":17,"discrimination":"chén：热（忱）\nshěn：（沈）阳\nzhěn：（枕）头\ndān：虎视（眈）（眈）","title":"热()","source":"2017桂林、2015玉林、防城港、2015河池","explanation":"热情。","label":2,"words":"热忱"},{"choose":["练","炼","链","恋"],"answer":"练","pinyin":"rén qíng liàn dá","id":18,"discrimination":"liàn：人情（练）达\n锻（炼）\n（链）接\n留（恋）","title":"人情()达","source":"2015南宁","explanation":"指通晓待人处世的经验。语出清·曹雪芹《红楼梦》第五回：“世事洞明皆学问，人情练达即文章。”","label":1,"words":"人情练达"},{"choose":["晴","情","睛","青"],"answer":"情","pinyin":"rén qíng shì gù","id":19,"discrimination":"qíng：人（情）世故\n（晴）天\nqīng：（青）菜\njīng：眼（睛）","title":"人()世故","source":"2017贺州","explanation":"指为人处世的方法、道理和经验。语出宋·文天祥《送僧了敬序》：“姑与之委曲于人情世故之内。”","label":2,"words":"人情世故"},{"choose":["峻","骏","竣","俊"],"answer":"俊","pinyin":"rěn jùn bù jīn","id":20,"discrimination":"jùn：忍（俊）不禁\n险（峻）\n（骏）马\n（竣）工","title":"忍()不禁","source":"2015来宾、2015梧州","explanation":"指忍不住笑出来。","label":4,"words":"忍俊不禁"},{"choose":["戎","溶","容","荣"],"answer":"荣","pinyin":"róng yīng","id":1,"discrimination":"róng：（荣）膺\n（戎）马\n（溶）液\n（容）易","title":"()膺","source":"2016百色","explanation":"光荣地接受或承当。语出唐·李商隐《为荥阳公与京兆李尹状》：“伏承荣膺新命，伏惟感慰。”","label":1,"words":"荣膺"},{"choose":["蓉","容","溶","熔"],"answer":"容","pinyin":"róng guāng huàn fā","id":2,"discrimination":"róng：（容）光焕发\n芙（蓉）\n（溶）液\n（熔）岩","title":"()光焕发","source":"2016北海","explanation":"脸上的光彩四射。形容身体健康、精神饱满。语出清·蒲松龄《聊斋志异》：“母亦喜；为女盥濯；竟妆；容光焕发。”","label":4,"words":"容光焕发"},{"choose":["溶","融","容","熔"],"answer":"融","pinyin":"róng huì guàn tōng","id":3,"discrimination":"róng：（融）会贯通\n（溶）液\n（容）颜\n（熔）岩","title":"()会贯通","source":"2016钦州","explanation":"融会：融合领会；贯通：透彻理解。指融合多方面的知识道理，得到全面、透彻的领悟。","label":1,"words":"融会贯通"},{"choose":["付","负","富","复"],"answer":"负","pinyin":"rú shì zhòng fù","id":4,"discrimination":"fù：如释重（负）\n（付）出\n（富）裕\n报（复）","title":"如释重()","source":"2015桂林","explanation":"像放下重担那样。形容紧张心情过去以后的轻松愉快。语出《谷梁传·昭公二十九年》：“昭公出奔；民如释重负。”","label":1,"words":"如释重负"},{"choose":["睿","眷","誉","誊"],"answer":"睿","pinyin":"ruì zhì","id":5,"discrimination":"ruì：（睿）智\njuàn：（眷）恋\nyù：荣（誉）\nténg：（誊）写","title":"()智","source":"2016百色","explanation":"英明有远见。语出《孔子家语·三恕》：“聪明睿智，守之以愚。”","label":2,"words":"睿智"},{"choose":["莘","锌","籽","梓"],"answer":"梓","pinyin":"sāng zǐ","id":6,"discrimination":"zǐ：桑（梓）\nshēn：（莘）（莘）学子\nxīn：（锌）粉","title":"桑()","source":"2014钦州","explanation":"古代常在家屋旁栽种桑树和梓树。又说家乡的桑树和梓树是父母种的，要对它表示敬意。后人用桑梓比喻故乡。语出《诗经·小雅·小弁》：“维桑与梓，必恭敬止。”","label":2,"words":"桑梓"},{"choose":["煞","邹","皱","刹"],"answer":"煞","pinyin":"shà yǒu jiè shì","id":7,"discrimination":"shà：（煞）有介事\nzōu：（邹）忌\nzhòu：（皱）眉","title":"()有介事","source":"2017桂林","explanation":"像真有这么一回事似的。多指故作姿态。语出宋·陆九渊《语录下》：“先生曰：‘某何尝不教人读书；不知此后煞有甚事。’”","label":2,"words":"煞有介事"},{"choose":["绷","崩","嘣","蹦"],"answer":"崩","pinyin":"shān bēng dì liè","id":8,"discrimination":"bēng：山（崩）地裂\n（绷）紧\n嘎（嘣）\nbèng：（蹦）跶","title":"山()地裂","source":"2015南宁、2014梧州","explanation":"形容响声巨大或变化剧烈。","label":2,"words":"山崩地裂"},{"choose":["姗姗","衫衫","扇扇","珊珊"],"answer":"姗姗","pinyin":"shān shān lái chí","id":9,"discrimination":"shān：（姗）（姗）来迟\n衬（衫）\n（扇）风\n（珊）瑚","title":"()()来迟","source":"2014梧州","explanation":"形容走得缓慢从容。慢腾腾地来晚了。语出《汉书·孝武李夫人传》：“立而望之，偏何姗姗其来迟。”","label":1,"words":"姗姗来迟"},{"choose":["灿","汕","讪","疝"],"answer":"讪","pinyin":"shàn xiào","id":10,"discrimination":"shàn：（讪）笑\n（汕）头\n（疝）气\ncàn：（灿）烂","title":"()笑","source":"2014贵港","explanation":"讥笑。语出《新唐书·韩愈传赞》：“ 愈独喟然引圣，争四海之惑，虽蒙讪笑，跲而复奋，始若未之信，卒大显於时。”","label":2,"words":"讪笑"},{"choose":["稍","梢","捎","邵"],"answer":"稍","pinyin":"shāo zòng jí shì","id":11,"discrimination":"shāo：（稍）纵即逝\n树（梢）\n（捎）带","title":"()纵即逝","source":"2016桂林、2015桂林","explanation":"形容时间或机会等很容易流逝。","label":4,"words":"稍纵即逝"},{"choose":["俭","简","检","睑"],"answer":"简","pinyin":"shēn jū jiǎn chū","id":12,"discrimination":"jiǎn：深居（简）出\n（俭）朴\n（检）查\n眼（睑）","title":"深居()出","source":"2017桂林","explanation":"简：简省。原指野兽藏在深密的地方，很少出现。后指平日在家里，很少出门。","label":1,"words":"深居简出"},{"choose":["熠熠","翌翌","奕奕","异异"],"answer":"奕奕","pinyin":"shén cǎi yì yì","id":13,"discrimination":"yì：神采（奕）（奕）\n闪（熠）\n（翌）日\n奇（异）","title":"神采()()","source":"2015玉林、防城港","explanation":"形容精力旺盛，容光焕发。","label":1,"words":"神采奕奕"},{"choose":["涯","崖","衙","捱"],"answer":"涯","pinyin":"shēng yá","id":14,"discrimination":"yá：生（涯）\n悬（崖）\nái：难（捱）","title":"生()","source":"2016贺州","explanation":"指从事某种活动或职业的生活经历。语出《庄子·养生主》：“吾生也有涯，而知也无涯。”","label":2,"words":"生涯"},{"choose":["菱","棱","凌","陵"],"answer":"凌","pinyin":"shèng qì líng rén","id":15,"discrimination":"líng：盛气（凌）人\n（菱）角\n（陵）园\nléng：（棱）角","title":"盛气()人","source":"2014梧州","explanation":"傲慢的气势逼人。语出清·曾国藩《求阙斋语》：“今日我以盛气凌人；预想他日人亦以盛气凌我。”","label":2,"words":"盛气凌人"},{"choose":["圆","原","源","园"],"answer":"源","pinyin":"shì wài táo yuán","id":16,"discrimination":"yuán：世外桃（源）\n（圆）形\n（原）来\n公（园）","title":"世外桃()","source":"2017广西北部湾经济区四市同城","explanation":"陶潜在《桃花源记》中描述了一个与世隔绝的不遭战祸的安乐而美好的地方。后借指不受外界影响的地方或幻想中的美好世界。","label":1,"words":"世外桃源"},{"choose":["敛","潋","俭","睑"],"answer":"敛","pinyin":"shōu liǎn","id":17,"discrimination":"liǎn：收（敛）\nliàn：（潋）滟\njiǎn：眼（睑）\n节（俭）","title":"收()","source":"2015百色","explanation":"1.（笑容、光线等）减弱或消失。2.减轻放纵的程度（指言行）。3.引起机体组织收缩，减少腺体分泌。","label":2,"words":"收敛"},{"choose":["手","守","狩","首"],"answer":"首","pinyin":"shǒu qū yī zhǐ","id":18,"discrimination":"shǒu：（首）屈一指\n（手）脚\n（守）护","title":"()屈一指","source":"2015北海","explanation":"屈指计数总是先屈大拇指，表示第一。指居第一位。引申为最好的。","label":1,"words":"首屈一指"},{"choose":["磷磷","嶙嶙","麟麟","粼粼"],"answer":"粼粼","pinyin":"shuǐ bō lín lín","id":19,"discrimination":"lín：水波（粼）（粼）\n（磷）火\n（嶙）峋\n麒（麟）","title":"水波()()","source":"2015南宁","explanation":"粼粼：水十分明净。形容水面明净。","label":4,"words":"水波粼粼"},{"choose":["哑","亚","雅","娅"],"answer":"哑","pinyin":"sī yǎ","id":20,"discrimination":"yǎ：嘶（哑）\nyà：（亚）洲\n姻（娅）","title":"嘶()","source":"2014桂林","explanation":"声音沙哑。","label":2,"words":"嘶哑"},{"choose":["榻","塌","蹋","踏"],"answer":"塌","pinyin":"sǐ xīn tā dì","id":1,"discrimination":"tā：死心（塌）地\ntà：床（榻）\n糟（蹋）\n脚（踏）实地","title":"死心()地","source":"2016河池、2015贺州、2016桂林","explanation":"原指死了心，不作别的打算。后常形容打定了主意，决不改变。","label":2,"words":"死心塌地"},{"choose":["唢","锁","琐","嗦"],"answer":"琐","pinyin":"suǒ xiè","id":2,"discrimination":"suǒ：（琐）屑\n（唢）呐\n（锁）链","title":"()屑","source":"2017贺州、2015南宁","explanation":"1.琐碎。2.生活中的小事。屑：碎末。","label":4,"words":"琐屑"},{"choose":["抵","底","邸","砥"],"answer":"砥","pinyin":"tǎn dàng rú dǐ","id":3,"discrimination":"dǐ：坦荡如（砥）\n（抵）达\n（底）层\n官（邸）","title":"坦荡如()","source":"2015玉林、防城港、2014北海","explanation":"平坦得像磨刀石一样。比喻人非常直率，不加犹豫。现多用来形容大面积的地方很平坦。出自《诗经·小雅·大东》：“周道如砥，其直如矢。”","label":4,"words":"坦荡如砥"},{"choose":["陶","淘","韬","滔"],"answer":"陶","pinyin":"táo yě","id":4,"discrimination":"táo：（陶）冶\n（淘）气\ntāo：文（韬）武略\n（滔）（滔）不绝","title":"()冶","source":"2014北海","explanation":"烧造陶器、冶炼金属。比喻对人的性格和思想进行培养。","label":3,"words":"陶冶"},{"choose":["轮","伦","仑","论"],"answer":"伦","pinyin":"tiān lún zhī lè","id":5,"discrimination":"lún：天（伦）之乐\n（轮）流\n昆（仑）山\n（论）语","title":"天()之乐","source":"2016梧州","explanation":"指老一辈和小一辈有血缘亲属关系之间的家庭乐趣。","label":4,"words":"天伦之乐"},{"choose":["拔","泼","跋","拨"],"answer":"拨","pinyin":"tiǎo bō lí jiàn","id":6,"discrimination":"bō：挑（拨）离间\nbá：（拔）河\n（跋）山涉水\npō：活（泼）","title":"挑()离间","source":"2014贵港","explanation":"搬弄是非，引起纠纷、事端，使别人不和。","label":2,"words":"挑拨离间"},{"choose":["佻","跳","挑","眺"],"answer":"挑","pinyin":"tiǎo xìn","id":7,"discrimination":"tiǎo：（挑）衅\ntiāo：轻（佻）\ntiào：（跳）跃\n远（眺）","title":"()衅","source":"2015来宾","explanation":"指借端生事，企图引起冲突或战争。","label":2,"words":"挑衅"},{"choose":["疾","急","极","籍"],"answer":"疾","pinyin":"tòng xīn jí shǒu","id":8,"discrimination":"jí：痛心（疾）首\n（急）忙\n积（极）\n书（籍）","title":"痛心()首","source":"2016桂林","explanation":"痛心： 心痛；疾首：头痛。形容痛恨到了极点。","label":1,"words":"痛心疾首"},{"choose":["烦","硕","顶","颓"],"answer":"颓","pinyin":"tuí táng","id":9,"discrimination":"tuí：（颓）唐\nfán：（烦）恼\nshuò：（硕）大\ndǐng：屋（顶）","title":"()唐","source":"2017贺州","explanation":"指衰颓败落，精神萎靡不振的样子。","label":2,"words":"颓唐"},{"choose":["贴","粘","沾","帖"],"answer":"帖","pinyin":"tuǒ tiē","id":10,"discrimination":"tiē：妥（帖）\n（贴）画\nnián：（粘）性\nzhān：均（沾）","title":"妥()","source":"2017广西北部湾经济区四市同城","explanation":"恰当，十分合适。","label":2,"words":"妥帖"},{"choose":["腕","碗","惋","婉"],"answer":"惋","pinyin":"wǎn xī","id":11,"discrimination":"wǎn：（惋）惜\n饭（碗）\n委（婉）\nwàn：手（腕）","title":"()惜","source":"2016柳州、2015桂林","explanation":"表示对某事感到同情、可惜。","label":2,"words":"惋惜"},{"choose":["慑","涉","赦","麝"],"answer":"赦","pinyin":"wàn è bù shè","id":12,"discrimination":"shè：万恶不（赦）\n震（慑）\n跋（涉）\n（麝）香","title":"万恶不()","source":"2014梧州","explanation":"形容一个人罪大恶极、不可饶恕。","label":1,"words":"万恶不赦"},{"choose":["惘","魍","网","往"],"answer":"惘","pinyin":"wǎng rán","id":13,"discrimination":"wǎng：（惘）然\n（魍）魉\n渔（网）\n过（往）","title":"()然","source":"2014钦州","explanation":"失意、心情迷茫的样子。","label":1,"words":"惘然"},{"choose":["福","蝠","幅","富"],"answer":"富","pinyin":"wéi fù bù rén","id":14,"discrimination":"fù：为（富）不仁\nfú：幸（福）\n蝙（蝠）\n条（幅）","title":"为()不仁","source":"2016河池","explanation":"剥削者为了发财致富，心狠手毒，没有一点儿仁慈的心肠。","label":2,"words":"为富不仁"},{"choose":["帷","维","唯","惟"],"answer":"帷","pinyin":"wéi mù","id":15,"discrimination":"wéi：（帷）幕\n（维）持\n（唯）恐\n（惟）独","title":"()幕","source":"2016梧州、2015百色","explanation":"悬挂起来用于遮挡的大块布、绸、丝绒等。","label":4,"words":"帷幕"},{"choose":["惟","唯","维","帷"],"answer":"惟","pinyin":"wéi miào wéi xiào","id":16,"discrimination":"wéi：（惟）妙惟肖\n（唯）恐\n（维）持\n（帷）幕","title":"()妙惟肖","source":"2015百色","explanation":"形容描写或模仿得非常逼真。","label":4,"words":"惟妙惟肖"},{"choose":["谬","缪","寥","蓼"],"answer":"缪","pinyin":"wèi yǔ chóu móu","id":17,"discrimination":"móu：未雨绸（缪）\nmiù：（谬）误\nliáo：寂（寥）\nliǎo：（蓼）蓝","title":"未雨绸()","source":"2017河池、2014河池","explanation":"趁着天没下雨，先修缮房屋门窗。比喻事先做好准备工作，预防意外的事发生。","label":2,"words":"未雨绸缪"},{"choose":["蓝","篮","澜","栏"],"answer":"蓝","pinyin":"wèi lán","id":18,"discrimination":"lán：蔚（蓝）\n摇（篮）\n波（澜）\n（栏）杆","title":"蔚()","source":"2014贺州","explanation":"用来形容类似晴朗天空的颜色的一种蓝色。","label":1,"words":"蔚蓝"},{"choose":["棘","藉","暨","羁"],"answer":"藉","pinyin":"wèi jiè","id":19,"discrimination":"jiè：慰（藉）\njí：荆（棘）\njì：越（暨）\njī：（羁）绊","title":"慰()","source":"2016百色、2015崇左","explanation":"安慰、抚慰。","label":3,"words":"慰藉"},{"choose":["湿","温","漫","蕴"],"answer":"温","pinyin":"wēn shēng xì yǔ","id":20,"discrimination":"wēn：（温）声细语\nshī：潮（湿）\nmàn：（漫）游\nyùn：（蕴）藏","title":"()声细语","source":"2017梧州","explanation":"温：温和；细语：小声地说话。用温和的声音轻轻地说话；声音温和而委婉，多形容女子。","label":2,"words":"温声细语"},{"choose":["馨","磬","罄","謦"],"answer":"馨","pinyin":"wēn xīn","id":1,"discrimination":"xīn：温（馨）\nqìng：（磬）工\n告（罄）\nqǐng：（謦）谈","title":"温()","source":"2017河池","explanation":"温和芳香；温暖。","label":2,"words":"温馨"},{"choose":["蓑","哀","衰","衷"],"answer":"衷","pinyin":"wú dòng yú zhōng","id":2,"discrimination":"zhōng：无动于（衷）\nsuō：（蓑）衣\nāi：（哀）伤\nshuāi：（衰）老","title":"无动于()","source":"2014来宾、2016桂林、2015南宁","explanation":"心里一点不受感动，一点也不动心。","label":2,"words":"无动于衷"},{"choose":["采","彩","踩","睬"],"answer":"采","pinyin":"wú jīng dǎ cǎi","id":3,"discrimination":"cǎi：无精打（采）\n（彩）色\n（踩）踏\n理（睬）","title":"无精打()","source":"2016贺州、2014百色","explanation":"形容精神不振，提不起劲头。","label":4,"words":"无精打采"},{"choose":["阑","澜","斓","谰"],"answer":"斓","pinyin":"wǔ cǎi bān lán","id":4,"discrimination":"lán：五彩斑（斓）\n灯火（阑）珊\n波（澜）\n（谰）言","title":"五彩斑()","source":"2017梧州、2015崇左、2016梧州","explanation":"斑斓：颜色驳杂，灿烂多彩。表示颜色非常好看，色彩相当丰富。","label":4,"words":"五彩斑斓"},{"choose":["竟","敬","竞","境"],"answer":"竞","pinyin":"wù jìng tiān zé","id":5,"discrimination":"jìng：物（竞）天择\n（竟）然\n尊（敬）\n（境）外","title":"物()天择","source":"2015来宾、2014贺州","explanation":"物竞：生物的生存竞争；天择：自然选择。生物相互竞争，能适应者生存下来。原指生物进化的一般规律，后也用于人类社会的发展。","label":1,"words":"物竞天择"},{"choose":["翼","骥","暨","冀"],"answer":"冀","pinyin":"xī jì","id":6,"discrimination":"jì：希（冀）\n按图索（骥）\n（暨）今\nyì：羽（翼）","title":"希()","source":"2015北海","explanation":"希望得到；非分的愿望。","label":3,"words":"希冀"},{"choose":["晰","淅","蜥","析"],"answer":"淅","pinyin":"xī lì","id":7,"discrimination":"xī：（淅）沥\n清（晰）\n（蜥）蜴\n（析）出","title":"()沥","source":"2014百色","explanation":"形容轻微的风雨声、落叶声等。","label":4,"words":"淅沥"},{"choose":["犀","膝","锡","曦"],"answer":"犀","pinyin":"xī lì","id":8,"discrimination":"xī：（犀）利\n（膝）盖\n（锡）纸\n晨（曦）","title":"()利","source":"2014贺州、2014河池","explanation":"（刀、剑等）锋利，锐利。也形容言词尖锐明快，目光锐利。","label":1,"words":"犀利"},{"choose":["娴","贤","闲","嫌"],"answer":"娴","pinyin":"xián shú","id":9,"discrimination":"xián：（娴）熟\n（贤）良\n休（闲）\n（嫌）弃","title":"()熟","source":"2015玉林、防城港、2014桂林","explanation":"老练、熟练或灵活，形容对某种事物或工作很熟练。","label":1,"words":"娴熟"},{"choose":["樟","障","璋","彰"],"answer":"彰","pinyin":"xiāng dé yì zhāng","id":10,"discrimination":"zhāng：相得益（彰）\n香（樟）\n弄（璋）\nzhàng：屏（障）","title":"相得益()","source":"2015贺州、2014梧州","explanation":"指互相帮助，互相补充，更能显出各自的好处。","label":2,"words":"相得益彰"},{"choose":["堤","提","题","缇"],"answer":"提","pinyin":"xiāng tí bìng lùn","id":11,"discrimination":"tí：相（提）并论\n命（题）\n（缇）绮\ndī：（堤）坝","title":"相()并论","source":"2017贺州、2014北海","explanation":"把不同的或相差悬殊的人或事物混在一起来谈论或看待（多用于否定式）。","label":2,"words":"相提并论"},{"choose":["础","拙","绌","茁"],"answer":"绌","pinyin":"xiāng xíng jiàn chù","id":12,"discrimination":"chù：相形见（绌）\nchǔ：基（础）\nzhuō：弄巧成（拙）\nzhuó：（茁）壮","title":"相形见()","source":"2014梧州","explanation":"跟另一人或事物比较起来显得远远不足。绌：不足。","label":2,"words":"相形见绌"},{"choose":["销","消","硝","逍"],"answer":"销","pinyin":"xiāo shēng nì jì","id":13,"discrimination":"xiāo：（销）声匿迹\n（消）除\n（硝）烟\n（逍）遥","title":"()声匿迹","source":"2015贺州、2015梧州","explanation":"不再公开讲话，不再出头露面。形容隐藏起来或不公开出现。","label":4,"words":"销声匿迹"},{"choose":["鞠","拘","据","掬"],"answer":"掬","pinyin":"xiào róng kě jū","id":14,"discrimination":"jū：笑容可（掬）\n（鞠）躬\n（拘）捕\n拮（据）","title":"笑容可()","source":"2015玉林、防城港","explanation":"掬：双手捧取。形容笑容满面。","label":1,"words":"笑容可掬"},{"choose":["犷","矿","旷","扩"],"answer":"旷","pinyin":"xīn kuàng shén yí","id":15,"discrimination":"kuàng：心（旷）神怡\n（矿）石\nguǎng：（犷）野\nkuò：（扩）大","title":"心()神怡","source":"2015梧州","explanation":"心情愉快,精神舒畅。","label":2,"words":"心旷神怡"},{"choose":["季","忌","荠","悸"],"answer":"悸","pinyin":"xīn yǒu yú jì","id":16,"discrimination":"jì：心有余（悸）\n（季）节\n（忌）讳\n（荠）菜","title":"心有余()","source":"2016河池","explanation":"危险的事情虽然过去了，回想起来还感到害怕。","label":1,"words":"心有余悸"},{"choose":["勃勃","渤渤","脖脖","鹁鹁"],"answer":"勃勃","pinyin":"xìng zhì bó bó","id":17,"discrimination":"bó：兴致（勃）（勃）\n（渤）海\n（脖）颈\n（鹁）鸠","title":"兴致()()","source":"2016桂林、2015河池","explanation":"兴致：兴趣；勃勃：旺盛的样子 。形容兴趣很浓厚，情绪很高涨的样子。","label":4,"words":"兴致勃勃"},{"choose":["姿","资","咨","滋"],"answer":"姿","pinyin":"xióng zī","id":18,"discrimination":"zī：雄（姿）\n（资）料\n（咨）询","title":"雄()","source":"2014南宁","explanation":"指勇武壮盛的意气或姿态。","label":4,"words":"雄姿"},{"choose":["颀","欣","颓","祈"],"answer":"颀","pinyin":"xiù qí","id":19,"discrimination":"qí：秀（颀）\nxīn：（欣）然\ntuí：（颓）废\nqí：（祈）求","title":"秀()","source":"2015河池","explanation":"美而高。颀，高。","label":2,"words":"秀颀"},{"choose":["秀","绣","锈","袖"],"answer":"袖","pinyin":"xiù shǒu páng guān","id":20,"discrimination":"xiù：（袖）手旁观\n（秀）色可餐\n刺（绣）\n铁（锈）","title":"()手旁观","source":"2016梧州","explanation":"把手笼在袖子里，在一旁观看。比喻人置身事外、不帮助别人。","label":1,"words":"袖手旁观"},{"choose":["炫","弦","玄","眩"],"answer":"炫","pinyin":"xuàn yào","id":1,"discrimination":"xuàn：（炫）耀\n（眩）晕\nxián：上（弦）\nxuán：（玄）虚","title":"()耀","source":"2015河池","explanation":"照耀；夸耀。","label":2,"words":"炫耀"},{"choose":["徇","绚","旬","询"],"answer":"绚","pinyin":"xuàn lì","id":2,"discrimination":"xuàn：（绚）丽\nxùn：（徇）私枉法\nxún：中（旬）\n（询）问\n","title":"()丽","source":"2016柳州","explanation":"耀眼而华丽。","label":2,"words":"绚丽"},{"choose":["据","距","矩","炬"],"answer":"矩","pinyin":"xún guī dǎo jǔ","id":3,"discrimination":"jǔ：循规蹈（矩）\njù：不足为（据）\n（距）离\n火（炬）","title":"循规蹈()","source":"2016河池、2014桂林","explanation":"原指遵守规矩，不敢违反。现也指拘守旧准则，不敢稍做变动。","label":2,"words":"循规蹈矩"},{"choose":["遁遁","旬旬","寻寻","循循"],"answer":"循循","pinyin":"xún xún shàn yòu","id":4,"discrimination":"xún：（循）（循）善诱\n下（旬）\n（寻）找\ndùn：（遁）词","title":"()()善诱","source":"2016钦州","explanation":"指善于引导别人进行学习。","label":3,"words":"循循善诱"},{"choose":["峋","绚","殉","询"],"answer":"殉","pinyin":"xùn zhí","id":5,"discrimination":"xùn：（殉）职\nxún：嶙（峋）\n（询）问\nxuàn：（绚）丽","title":"()职","source":"2017贺州","explanation":"指的是某个职务人员因为公务事而死亡，是一个褒义词。","label":2,"words":"殉职"},{"choose":["雅","鸦","鸭","哑"],"answer":"鸦","pinyin":"yā què wú shēng","id":6,"discrimination":"yā：（鸦）雀无声\n（鸭）梨\nyǎ：高（雅）\n（哑）语","title":"()雀无声","source":"2016崇左、2014钦州、2016百色","explanation":"连乌鸦麻雀的声音都没有。形容非常静。","label":3,"words":"鸦雀无声"},{"choose":["该","赅","骇","垓"],"answer":"赅","pinyin":"yán jiǎn yì gāi","id":7,"discrimination":"gāi：言简意（赅）\n应（该）\n（垓）下之围\nhài：（骇）人听闻","title":"言简意()","source":"2014桂林","explanation":"指形容言语简练而意思完整。赅：完备。","label":2,"words":"言简意赅"},{"choose":["俨","严","焉","掩"],"answer":"俨","pinyin":"yǎn rán","id":8,"discrimination":"yǎn：（俨）然\n（掩）盖\nyán：（严）肃\nyān：（焉）知","title":"()然","source":"2017广西北部湾经济区四市同城","explanation":"形容庄重、严肃；形容整齐的样子；形容特别像，非常地像，简直就是某物。","label":3,"words":"俨然"},{"choose":["应","秧","殃","映"],"answer":"映","pinyin":"yǎn yìng","id":9,"discrimination":"yìng：掩（映）\nyāng：插（秧）\n遭（殃）","title":"掩()","source":"2014桂林","explanation":"彼此遮掩而互相衬托。","label":2,"words":"掩映"},{"choose":["瞭","僚","燎","缭"],"answer":"缭","pinyin":"yǎn huā liáo luàn","id":10,"discrimination":"liáo：眼花（缭）乱\n同（僚）\n（燎）泡\nliào：（瞭）望","title":"眼花()乱","source":"2017桂林、2014梧州、2015河池","explanation":"眼睛看见复杂纷繁的东西而感到迷乱。","label":2,"words":"眼花缭乱"},{"choose":["幕","募","慕","暮"],"answer":"慕","pinyin":"yǎng mù","id":11,"discrimination":"mù：仰（慕）\n（幕）布\n（募）捐\n（暮）色","title":"仰()","source":"2015南宁","explanation":"敬仰思慕。","label":4,"words":"仰慕"},{"choose":["怏怏","央央","映映","殃殃"],"answer":"怏怏","pinyin":"yàng yàng bù lè","id":12,"discrimination":"yàng：（怏）（怏）不乐\nyāng：（央）求\n遭（殃）\nyìng：反（映）","title":"()()不乐","source":"2014梧州","explanation":"怏怏：形容不满意或不高兴的神情。心中郁闷，很不快活。","label":2,"words":"怏怏不乐"},{"choose":["吆","幺","夭","幼"],"answer":"吆","pinyin":"yāo he","id":13,"discrimination":"yāo：（吆）喝\n（幺）蛾子\nyòu：（幼）小","title":"()喝","source":"2016百色","explanation":"大声喊叫（多指叫卖东西、赶牲口、呼唤等）。","label":2,"words":"吆喝"},{"choose":["娆","侥","饶","绕"],"answer":"娆","pinyin":"yāo ráo","id":14,"discrimination":"ráo：妖（娆）\n丰（饶）\njiǎo：（侥）幸\nrào：环（绕）","title":"妖()","source":"2016河池、2014河池","explanation":"娇艳美好；妩媚多姿。","label":2,"words":"妖娆"},{"choose":["蓝","篮","栏","阑"],"answer":"篮","pinyin":"yáo lán","id":15,"discrimination":"lán：摇（篮）\n（蓝）天\n（栏）杆\n（阑）尾","title":"摇()","source":"2015贺州","explanation":"1.供婴儿睡觉的家具，形状略像篮子，多用竹或藤制成，可以左右摇动，使婴儿容易入睡。2.比喻幼年或青年时代的生活环境或文化、运动等的发源地。","label":1,"words":"摇篮"},{"choose":["戈","曳","谒","弋"],"answer":"曳","pinyin":"yáo yè","id":16,"discrimination":"yè：摇（曳）\n拜（谒）\ngē：（戈）壁\nyì：游（弋）","title":"摇()","source":"2014河池","explanation":"指逍遥，形容东西在风中轻轻摆动的样子。","label":3,"words":"摇曳"},{"choose":["决","诀","块","抉"],"answer":"诀","pinyin":"yào jué","id":17,"discrimination":"jué：要（诀）\n解（决）\n（抉）择\nkuài：石（块）","title":"要()","source":"2016百色","explanation":"指关键的窍门、重要的诀窍。","label":2,"words":"要诀"},{"choose":["娇","矫","轿","骄"],"answer":"骄","pinyin":"yī dài tiān jiāo","id":18,"discrimination":"jiāo：一代天（骄）\n（娇）弱\njiǎo：（矫）正\njiào：花（轿）","title":"一代天()","source":"2015梧州","explanation":"指能称雄一世的人物。天骄：“天之骄子”的省略语。汉朝时匈奴单于自称为天之骄子，后来称历史上某些强盛的北方少数民族君主为天骄。","label":2,"words":"一代天骄"},{"choose":["合","和","河","荷"],"answer":"合","pinyin":"yī pāi jí hé","id":19,"discrimination":"hé：一拍即（合）\n平（和）\n（河）流\n（荷）花","title":"一拍即()","source":"2016南宁","explanation":"拍：乐曲的段落，也称打拍子。一打拍子就合上了曲子的节奏。比喻很快就和谐一致了。","label":1,"words":"一拍即合"},{"choose":["抔","不","怀","杯"],"answer":"抔","pinyin":"yī póu huáng tǔ","id":20,"discrimination":"póu：一（抔）黄土\nbù：（不）求甚解\nhuái：胸（怀）\nbēi：干（杯）","title":"一()黄土","source":"2015百色","explanation":"借指坟墓。现多比喻不多的土地或没落、渺小的反动势力。","label":2,"words":"一抔黄土"},{"choose":["呵","坷","珂","阿"],"answer":"呵","pinyin":"yī qì hē chéng","id":1,"discrimination":"hē：一气（呵）成\nkě：坎（坷）\nkē：玉（珂）\nā：（阿）姨","title":"一气()成","source":"2016南宁","explanation":"形容文章结构紧凑，文气连贯。也比喻做一件事情安排紧凑，迅速不间断地完成。","label":2,"words":"一气呵成"},{"choose":["泄","泻","屑","卸"],"answer":"泻","pinyin":"yī  xiè qiān lǐ","id":2,"discrimination":"xiè：一（泻）千里\n（泄）露\n琐（屑）\n（卸）职","title":"一()千里","source":"2016河池、2015梧州","explanation":"形容江河水流迅速，也形容文笔奔放，流畅。","label":1,"words":"一泻千里"},{"choose":["鹰","膺","缨","莺"],"answer":"膺","pinyin":"yì fèn tián yīng","id":3,"discrimination":"yīng：义愤填（膺）\n老（鹰）\n长（缨）\n夜（莺）","title":"义愤填()","source":"2017桂林、2014来宾、2016南宁","explanation":"胸中充满了正义的愤恨，形容十分愤怒。","label":1,"words":"义愤填膺"},{"choose":["工","功","弓","公"],"answer":"工","pinyin":"yì qǔ tóng gōng","id":4,"discrimination":"gōng：异曲同（工）\n练（功）\n（弓）箭\n（公）园","title":"异曲同()","source":"2016钦州","explanation":"曲调虽然不同，却都同样美妙。比喻不同的说法或做法都收到同样的效果。","label":1,"words":"异曲同工"},{"choose":["锉","挫","措","搓"],"answer":"挫","pinyin":"yì yáng dùn cuò","id":5,"discrimination":"cuò：抑扬顿（挫）\n（锉）刀\n（措）施\ncuō：（搓）洗","title":"抑扬顿()","source":"2015梧州、2014贵港、2014钦州","explanation":"指声音高低曲折，十分和谐。多用于形容悦耳的声音。","label":3,"words":"抑扬顿挫"},{"choose":["益","缢","谥","溢"],"answer":"溢","pinyin":"yì yú yán biǎo","id":6,"discrimination":"yì：（溢）于言表\n公（益）\n自（缢）\nshì：（谥）号","title":"()于言表","source":"2016钦州","explanation":"（感情）流露在言辞、神情上。","label":2,"words":"溢于言表"},{"choose":["治","置","制","质"],"answer":"制","pinyin":"yīn dì zhì yí","id":7,"discrimination":"zhì：因地（制）宜\n（治）安\n处（置）\n（质）量","title":"因地()宜","source":"2017河池、2017广西北部湾经济区四市同城","explanation":"根据各地的具体情况，制定适宜的办法。","label":1,"words":"因地制宜"},{"choose":["霜","雾","霾","雳"],"answer":"霾","pinyin":"yīn mái","id":8,"discrimination":"mái：阴（霾）\nshuāng：冰（霜）\nwù：烟（雾）\nlì：霹（雳）","title":"阴()","source":"2015河池","explanation":"1.霾的通称。2.比喻环境恶劣。","label":2,"words":"阴霾"},{"choose":["闭","痹","壁","庇"],"answer":"庇","pinyin":"yìn bì","id":9,"discrimination":"bì：荫（庇）\n封（闭）\n麻（痹）\n（壁）虎","title":"荫()","source":"2015崇左","explanation":"大树枝叶遮蔽阳光，宜于人们休息，比喻尊长照顾晚辈或祖宗保佑子孙。","label":1,"words":"荫庇"},{"choose":["音","谙","喑","黯"],"answer":"喑","pinyin":"yīn yǎ","id":10,"discrimination":"yīn：（喑）哑\n声（音） \nān：（谙）熟\nàn：（黯）然","title":"()哑","source":"2014来宾","explanation":"指嗓子干涩发不出声音或发声低而不清楚。","label":2,"words":"喑哑"},{"choose":["倨","锯","剧","据"],"answer":"据","pinyin":"yǐn jīng jù diǎn","id":11,"discrimination":"jù：引经（据）典\n（倨）傲\n电（锯）\n（剧）本","title":"引经()典","source":"2017河池","explanation":"指引用经典著作中的语句或故事。","label":4,"words":"引经据典"},{"choose":["匿","偌","箬","诺"],"answer":"匿","pinyin":"yǐn nì","id":12,"discrimination":"nì：隐（匿）\nruò：（偌）大\n（箬）帽\nnuò：（诺）言","title":"隐()","source":"2016梧州","explanation":"隐藏，躲起来。","label":2,"words":"隐匿"},{"choose":["充充","冲冲","憧憧","忡忡"],"answer":"忡忡","pinyin":"yōu xīn chōng chōng","id":13,"discrimination":"chōng：忧心（忡）（忡）\n（充）满\n（冲）剂\n（憧）憬","title":"忧心()()","source":"2015梧州","explanation":"形容心事重重，非常忧愁，在担心着什么。忧：忧愁，忧虑。忡忡：忧虑不安的样子。","label":1,"words":"忧心忡忡"},{"choose":["鉴","銮","釜","签"],"answer":"鉴","pinyin":"yóu guāng kě jiàn","id":14,"discrimination":"jiàn：油光可（鉴）\nluán：金（銮）殿\nfǔ：（釜）山\nqiān：（签）字","title":"油光可()","source":"2015贺州","explanation":"头发上抹油，梳得很光亮，像镜子一样可以照人。形容非常光亮润泽。鉴：照。","label":2,"words":"油光可鉴"},{"choose":["具","惧","飓","俱"],"answer":"俱","pinyin":"yǔ rì jù zēng","id":15,"discrimination":"jù：与日（俱）增\n道（具）\n（惧）怕\n（飓）风","title":"与日()增","source":"2015北海","explanation":"用于人的思想感情，指随着时间的推移而不断增长。","label":4,"words":"与日俱增"},{"choose":["轮","仑","抡","伦"],"answer":"伦","pinyin":"yǔ wú lún cì","id":16,"discrimination":"lún：语无（伦）次\n（轮）船\n加（仑）\n（抡）锤","title":"语无()次","source":"2015南宁","explanation":"指话说得颠三倒四，言语没有条理层次。","label":4,"words":"语无伦次"},{"choose":["青","轻","清","倾"],"answer":"清","pinyin":"yuè míng fēng qīng","id":17,"discrimination":"qīng：月明风（清）\n（青）菜\n（轻）盈\n（倾）听","title":"月明风()","source":"2014南宁","explanation":"月光明朗，清风微动，用来形容美好的月夜。也比喻清闲无事。常用作衬托环境。","label":1,"words":"月明风清"},{"choose":["霄","宵","销","硝"],"answer":"霄","pinyin":"yún xiāo","id":18,"discrimination":"xiāo：云（霄）\n（宵）夜\n（销）蚀\n（硝）烟","title":"云()","source":"2016贺州","explanation":"极高的天空。","label":4,"words":"云霄"},{"choose":["踉","酿","琅","稂"],"answer":"酿","pinyin":"yùn niàng","id":19,"discrimination":"niàng：酝（酿）\nliàng：（踉）跄\nláng：珐（琅）\n（稂）莠不齐","title":"酝()","source":"2014贺州、2014来宾","explanation":"本意是造酒的发酵过程，也可以指事情逐渐成熟的准备过程。","label":2,"words":"酝酿"},{"choose":["励","历","厉","砺"],"answer":"厉","pinyin":"zài jiē zài lì","id":20,"discrimination":"lì：再接再（厉）\n鼓（励）\n（历）经磨难\n砥（砺）","title":"再接再()","source":"2015北海","explanation":"接：接战、迎战；厉：磨快，引申为奋勉，努力。形容一次又一次加倍努力。","label":4,"words":"再接再厉"},{"choose":["崭","斩","展","辗"],"answer":"斩","pinyin":"zhǎn dīng jié tiě","id":1,"discrimination":"zhǎn：（斩）钉截铁\n（崭）新\n（展）示\n（辗）转","title":"()钉截铁","source":"2016北海","explanation":"砍断钉子切断铁，形容说话或行动坚决果断，毫不犹豫。","label":1,"words":"斩钉截铁"},{"choose":["斩","暂","惭","崭"],"answer":"崭","pinyin":"zhǎn lù tóu jiǎo","id":2,"discrimination":"zhǎn：（崭）露头角\n（斩）断\nzàn：（暂）时\ncán：（惭）愧","title":"()露头角","source":"2015玉林、防城港、2014北海","explanation":"崭：突出；露：显露。头上的角已明显地突出来了。指初显露优异的才能。","label":2,"words":"崭露头角"},{"choose":["碾","展","搌","辗"],"answer":"辗","pinyin":"zhǎn zhuǎn","id":3,"discrimination":"zhǎn：（辗）转\n舒（展）\n（搌）布\nniǎn：（碾）压","title":"()转","source":"2014崇左","explanation":"指反复不定，翻来覆去的样子。","label":2,"words":"辗转"},{"choose":["绽","锭","靛","淀"],"answer":"绽","pinyin":"zhàn kāi","id":4,"discrimination":"zhàn：（绽）开\ndìng：纱（锭）\ndiàn：（靛）蓝\n（淀）粉","title":"()开","source":"2016崇左","explanation":"指植物的皮、壳等裂开，花儿开放，也比喻人们的笑脸。","label":2,"words":"绽开"},{"choose":["隍","篁","煌","皇"],"answer":"皇","pinyin":"zhāng huáng shī cuò","id":5,"discrimination":"huáng：张（皇）失措\n城（隍）庙\n（篁）阵\n辉（煌）","title":"张()失措","source":"2016百色、2015崇左、2015来宾","explanation":"形容慌慌张张，不知怎么办才好。","label":4,"words":"张皇失措"},{"choose":["跋","拔","钹","拨"],"answer":"跋","pinyin":"cháng tú bá shè","id":6,"discrimination":"bá：长途（跋）涉\n（拔）河\nbó：门（钹）\nbō：（拨）开","title":"长途()涉","source":"2016梧州","explanation":"跋涉：翻山越岭、趟水过河。指远距离的翻山渡水。形容路途遥远，行路辛苦。","label":2,"words":"长途跋涉"},{"choose":["吁","虚","需","须"],"answer":"吁","pinyin":"cháng xū duǎn tàn","id":7,"discrimination":"xū：长（吁）短叹\n（虚）弱\n（需）要\n胡（须）","title":"长()短叹","source":"2014贵港","explanation":"吁：叹息。因伤感、烦闷、痛苦等不住地唉声叹气。","label":1,"words":"长吁短叹"},{"choose":["褶","熠","翳","翌"],"answer":"褶","pinyin":"zhě zhòu","id":8,"discrimination":"zhě：（褶）皱\nyì：（熠）然\nyì：阴（翳）\n（翌）日","title":"()皱","source":"2014贵港","explanation":"1.由于地壳运动，岩层受到压力而形成的连续弯曲的构造形式。2.皱纹。","label":2,"words":"褶皱"},{"choose":["谛","啼","帝","蒂"],"answer":"谛","pinyin":"zhēn dì","id":9,"discrimination":"dì：真（谛）\n（帝）王\n瓜熟（蒂）落\ntí：（啼）哭","title":"真()","source":"2016南宁、2014百色","explanation":"真实的意义或道理。","label":2,"words":"真谛"},{"choose":["震","振","阵","镇"],"answer":"振","pinyin":"zhèn fèn","id":10,"discrimination":"zhèn：（振）奋\n（震）耳欲聋\n（阵）地\n（镇）守","title":"()奋","source":"2014北海","explanation":"指振作精神，奋发努力。","label":1,"words":"振奋"},{"choose":["振","震","阵","镇"],"answer":"震","pinyin":"zhèn ěr yù lóng","id":11,"discrimination":"zhèn：（震）耳欲聋\n（振）作\n（阵）地\n（镇）守","title":"()耳欲聋","source":"2016北海","explanation":"欲：快要，就要。形容声音很大。","label":1,"words":"震耳欲聋"},{"choose":["争","峥","挣","铮"],"answer":"峥","pinyin":"zhēng róng","id":12,"discrimination":"zhēng：（峥）嵘\n（争）斗\n（挣）扎\n（铮）（铮）铁骨","title":"()嵘","source":"2016崇左","explanation":"形容山的高峻突兀或建筑物的高大耸立，也指高峻的山峰。","label":4,"words":"峥嵘"},{"choose":["挚","直","纨","执"],"answer":"执","pinyin":"zhí niù","id":13,"discrimination":"zhí：（执）拗\nzhì：真（挚）\nwán：（纨）绔","title":"()拗","source":"2014百色","explanation":"形容固执任性，坚持己见，听不进别人的意见。也有阻拦的意思。","label":2,"words":"执拗"},{"choose":["抵","邸","砥","坻"],"answer":"砥","pinyin":"zhōng liú dǐ zhù","id":14,"discrimination":"dǐ：中流（砥）柱\n（抵）挡\n官（邸）\n岩（坻）","title":"中流()柱","source":"2016南宁、2015梧州","explanation":"指就像屹立在黄河急流中的砥柱山一样，比喻坚强独立的人能在动荡艰难的环境中起支柱作用。","label":4,"words":"中流砥柱"},{"choose":["彰","璋","障","嶂"],"answer":"嶂","pinyin":"chóng luán dié zhàng","id":15,"discrimination":"zhàng：重峦叠（嶂）\n一叶（障）目\nzhāng：欲盖弥（彰）\n弄（璋）之喜","title":"重峦叠()","source":"2017桂林、2014崇左、2014玉林、防城港、2015桂林","explanation":"重重叠叠的山峰。","label":2,"words":"重峦叠嶂"},{"choose":["绪","蓄","畜","絮"],"answer":"蓄","pinyin":"zhù xù","id":16,"discrimination":"xù：贮（蓄）\n情（绪）\n（畜）牧\n柳（絮）","title":"贮()","source":"2017广西北部湾经济区四市同城","explanation":"储存，积聚，指储存的物品。把节约下来或暂时不用的钱存起来。多指存到银行里，或放在仓库里。也指积存的钱。","label":1,"words":"贮蓄"},{"choose":["抹","沫","末","摩"],"answer":"抹","pinyin":"zhuǎn wān mò jiǎo","id":17,"discrimination":"mò：转弯（抹）角\n泡（沫）\n（末）尾","title":"转弯()角","source":"2016南宁","explanation":"沿着弯弯曲曲的路走。形容说话绕弯，不直截了当。","label":4,"words":"转弯抹角"},{"choose":["塑","朔","槊","溯"],"answer":"溯","pinyin":"zhuī sù","id":18,"discrimination":"sù：追（溯）\n（塑）料\nshuò：（朔）方\n横（槊）赋诗","title":"追()","source":"2016梧州","explanation":"逆流而上，向江河发源处走，比喻探索事物的由来。","label":2,"words":"追溯"},{"choose":["孜孜","牧牧","滋滋","咨咨"],"answer":"孜孜","pinyin":"zī zī bù juàn","id":19,"discrimination":"zī：（孜）（孜）不倦\n潜（滋）暗长\n（咨）询\nmù：（牧）羊","title":"()()不倦","source":"2017梧州、2017贺州","explanation":"孜孜：勤勉，不懈怠。通常指教师或学生工作或学习勤奋不知疲倦。","label":3,"words":"孜孜不倦"},{"choose":["栽","裁","载","截"],"answer":"裁","pinyin":"zì chū xīn cái","id":20,"discrimination":"cái：自出心（裁）\nzāi：（栽）树\nzǎi：三年五（载）\njié：直（截）了当","title":"自出心()","source":"2017广西北部湾经济区四市同城","explanation":"出于自己心意的创造和裁断。裁：设计。心裁：心中的设计、构思、筹划。","label":2,"words":"自出心裁"},{"choose":["原","渊","远","源"],"answer":"源","pinyin":"zuǒ yòu féng yuán","id":1,"discrimination":"yuán：左右逢（源）\n（原）野\nyuān：深（渊）\nyuǎn：（远）方","title":"左右逢()","source":"2016南宁","explanation":"原意是做学问工夫到家后就能用之不尽，取之不竭。后指做事得心应手，非常顺利。也用以比喻为人圆滑，两头讨好。","label":3,"words":"左右逢源"}]